<?xml version="1.0" encoding="UTF-8" standalone="no"?>
<xbrli:xbrl xmlns:xbrli="http://www.xbrl.org/2003/instance"
            xmlns:basis="http://xbrl.dcca.dk/Regnskab 2.0 Basis"
            xmlns:fsa="http://xbrl.dcca.dk/fsa"
            xmlns:arr="http://xbrl.dcca.dk/arr"
            xmlns:xl="http://www.xbrl.org/2003/XLink"
            xmlns:xhtml="http://www.w3.org/1999/xhtml"
            xmlns:lnk="http://www.xbrl.org/2003/linkbase"
            xmlns:ix="http://www.xbrl.org/2008/inlineXBRL"
            xmlns:link="http://www.xbrl.org/2003/linkbase"
            xmlns:xs="http://www.w3.org/2001/XMLSchema"
            xmlns:cmn="http://xbrl.dcca.dk/cmn"
            xmlns:dst="http://xbrl.dcca.dk/dst"
            xmlns:xbrldt="http://xbrl.org/2005/xbrldt"
            xmlns:gsd="http://xbrl.dcca.dk/gsd"
            xmlns:ifrs="http://xbrl.iasb.org/taxonomy/2009-04-01/ifrs"
            xmlns:xbrldi="http://xbrl.org/2006/xbrldi"
            xmlns:ref="http://www.xbrl.org/2006/ref"
            xmlns:mrv="http://xbrl.dcca.dk/mrv"
            xmlns:xlink="http://www.w3.org/1999/xlink"
            xmlns:ixt="http://www.xbrl.org/inlineXBRL/transformation/2010-04-20"
            xmlns:xsi="http://www.w3.org/2001/XMLSchema-instance"
            xmlns:sob="http://xbrl.dcca.dk/sob"
            xmlns:iso4217="http://www.xbrl.org/2003/iso4217">
   <lnk:schemaRef xlink:href="http://archprod.service.eogs.dk/taxonomy/20120101/entryDanishGAAPBalanceSheetAccountFormIncomeStatementByNatureIncludingManagementsReviewStatisticsAndTax20120101.xsd"
                  xlink:type="simple"/>
   <xbrli:context id="duration_only">
      <xbrli:entity>
         <xbrli:identifier scheme="http://www.dcca.dk/cvr">20378042</xbrli:identifier>
      </xbrli:entity>
      <xbrli:period>
         <xbrli:startDate>2012-01-01</xbrli:startDate>
         <xbrli:endDate>2012-12-31</xbrli:endDate>
      </xbrli:period>
   </xbrli:context>
   <xbrli:context id="duration_memberOfExecutiveBoardIdentifier_1">
      <xbrli:entity>
         <xbrli:identifier scheme="http://www.dcca.dk/cvr">20378042</xbrli:identifier>
      </xbrli:entity>
      <xbrli:period>
         <xbrli:startDate>2012-01-01</xbrli:startDate>
         <xbrli:endDate>2012-12-31</xbrli:endDate>
      </xbrli:period>
      <xbrli:scenario>
         <xbrldi:typedMember dimension="cmn:IdentificationOfMemberOfExecutiveBoardDimension">
            <cmn:memberOfBoardIdentifier>1</cmn:memberOfBoardIdentifier>
         </xbrldi:typedMember>
      </xbrli:scenario>
   </xbrli:context>
   <xbrli:context id="duration_memberOfSupervisoryBoardIdentifier_1">
      <xbrli:entity>
         <xbrli:identifier scheme="http://www.dcca.dk/cvr">20378042</xbrli:identifier>
      </xbrli:entity>
      <xbrli:period>
         <xbrli:startDate>2012-01-01</xbrli:startDate>
         <xbrli:endDate>2012-12-31</xbrli:endDate>
      </xbrli:period>
      <xbrli:scenario>
         <xbrldi:typedMember dimension="cmn:IdentificationOfMemberOfSupervisoryBoardDimension">
            <cmn:memberOfBoardIdentifier>1</cmn:memberOfBoardIdentifier>
         </xbrldi:typedMember>
      </xbrli:scenario>
   </xbrli:context>
   <xbrli:context id="duration_memberOfSupervisoryBoardIdentifier_2">
      <xbrli:entity>
         <xbrli:identifier scheme="http://www.dcca.dk/cvr">20378042</xbrli:identifier>
      </xbrli:entity>
      <xbrli:period>
         <xbrli:startDate>2012-01-01</xbrli:startDate>
         <xbrli:endDate>2012-12-31</xbrli:endDate>
      </xbrli:period>
      <xbrli:scenario>
         <xbrldi:typedMember dimension="cmn:IdentificationOfMemberOfSupervisoryBoardDimension">
            <cmn:memberOfBoardIdentifier>2</cmn:memberOfBoardIdentifier>
         </xbrldi:typedMember>
      </xbrli:scenario>
   </xbrli:context>
   <xbrli:context id="duration_memberOfSupervisoryBoardIdentifier_3">
      <xbrli:entity>
         <xbrli:identifier scheme="http://www.dcca.dk/cvr">20378042</xbrli:identifier>
      </xbrli:entity>
      <xbrli:period>
         <xbrli:startDate>2012-01-01</xbrli:startDate>
         <xbrli:endDate>2012-12-31</xbrli:endDate>
      </xbrli:period>
      <xbrli:scenario>
         <xbrldi:typedMember dimension="cmn:IdentificationOfMemberOfSupervisoryBoardDimension">
            <cmn:memberOfBoardIdentifier>3</cmn:memberOfBoardIdentifier>
         </xbrldi:typedMember>
      </xbrli:scenario>
   </xbrli:context>
   <xbrli:context id="duration_auditorIdentifier_1">
      <xbrli:entity>
         <xbrli:identifier scheme="http://www.dcca.dk/cvr">20378042</xbrli:identifier>
      </xbrli:entity>
      <xbrli:period>
         <xbrli:startDate>2012-01-01</xbrli:startDate>
         <xbrli:endDate>2012-12-31</xbrli:endDate>
      </xbrli:period>
      <xbrli:scenario>
         <xbrldi:typedMember dimension="arr:IdentificationOfAuditorDimension">
            <arr:auditorIdentifier>1</arr:auditorIdentifier>
         </xbrldi:typedMember>
      </xbrli:scenario>
   </xbrli:context>
   <xbrli:context id="duration_only_previous">
      <xbrli:entity>
         <xbrli:identifier scheme="http://www.dcca.dk/cvr">20378042</xbrli:identifier>
      </xbrli:entity>
      <xbrli:period>
         <xbrli:startDate>2011-01-01</xbrli:startDate>
         <xbrli:endDate>2011-12-31</xbrli:endDate>
      </xbrli:period>
   </xbrli:context>
   <xbrli:context id="duration_ProposedDividendRecognisedInEquityMember">
      <xbrli:entity>
         <xbrli:identifier scheme="http://www.dcca.dk/cvr">20378042</xbrli:identifier>
      </xbrli:entity>
      <xbrli:period>
         <xbrli:startDate>2012-01-01</xbrli:startDate>
         <xbrli:endDate>2012-12-31</xbrli:endDate>
      </xbrli:period>
      <xbrli:scenario>
         <xbrldi:explicitMember dimension="fsa:ResultDistributionDimension">fsa:ProposedDividendRecognisedInEquityMember</xbrldi:explicitMember>
      </xbrli:scenario>
   </xbrli:context>
   <xbrli:context id="duration_ProposedDividendRecognisedInEquityMember_previous">
      <xbrli:entity>
         <xbrli:identifier scheme="http://www.dcca.dk/cvr">20378042</xbrli:identifier>
      </xbrli:entity>
      <xbrli:period>
         <xbrli:startDate>2011-01-01</xbrli:startDate>
         <xbrli:endDate>2011-12-31</xbrli:endDate>
      </xbrli:period>
      <xbrli:scenario>
         <xbrldi:explicitMember dimension="fsa:ResultDistributionDimension">fsa:ProposedDividendRecognisedInEquityMember</xbrldi:explicitMember>
      </xbrli:scenario>
   </xbrli:context>
   <xbrli:context id="duration_RetainedEarningsMember">
      <xbrli:entity>
         <xbrli:identifier scheme="http://www.dcca.dk/cvr">20378042</xbrli:identifier>
      </xbrli:entity>
      <xbrli:period>
         <xbrli:startDate>2012-01-01</xbrli:startDate>
         <xbrli:endDate>2012-12-31</xbrli:endDate>
      </xbrli:period>
      <xbrli:scenario>
         <xbrldi:explicitMember dimension="fsa:ResultDistributionDimension">fsa:RetainedEarningsMember</xbrldi:explicitMember>
      </xbrli:scenario>
   </xbrli:context>
   <xbrli:context id="duration_RetainedEarningsMember_previous">
      <xbrli:entity>
         <xbrli:identifier scheme="http://www.dcca.dk/cvr">20378042</xbrli:identifier>
      </xbrli:entity>
      <xbrli:period>
         <xbrli:startDate>2011-01-01</xbrli:startDate>
         <xbrli:endDate>2011-12-31</xbrli:endDate>
      </xbrli:period>
      <xbrli:scenario>
         <xbrldi:explicitMember dimension="fsa:ResultDistributionDimension">fsa:RetainedEarningsMember</xbrldi:explicitMember>
      </xbrli:scenario>
   </xbrli:context>
   <xbrli:context id="instant_only">
      <xbrli:entity>
         <xbrli:identifier scheme="http://www.dcca.dk/cvr">20378042</xbrli:identifier>
      </xbrli:entity>
      <xbrli:period>
         <xbrli:instant>2012-12-31</xbrli:instant>
      </xbrli:period>
   </xbrli:context>
   <xbrli:context id="instant_only_previous">
      <xbrli:entity>
         <xbrli:identifier scheme="http://www.dcca.dk/cvr">20378042</xbrli:identifier>
      </xbrli:entity>
      <xbrli:period>
         <xbrli:instant>2011-12-31</xbrli:instant>
      </xbrli:period>
   </xbrli:context>
   <xbrli:unit id="DKK">
      <xbrli:measure>iso4217:DKK</xbrli:measure>
   </xbrli:unit>
   <gsd:InformationOnTypeOfSubmittedReport basis:ancestor="generelInfo" basis:version="1" contextRef="duration_only">Årsrapport</gsd:InformationOnTypeOfSubmittedReport>
   <gsd:DateOfGeneralMeeting basis:ancestor="generalMeetingDetails" contextRef="duration_only">2013-04-18</gsd:DateOfGeneralMeeting>
   <gsd:NameAndSurnameOfChairmanOfGeneralMeeting basis:ancestor="generalMeetingDetails" contextRef="duration_only">Benny Klitbo</gsd:NameAndSurnameOfChairmanOfGeneralMeeting>
   <gsd:NameOfReportingEntity basis:ancestor="generelInfo" contextRef="duration_only">BARNEY'S MALERFIRMA A/S</gsd:NameOfReportingEntity>
   <gsd:AddressOfReportingEntityStreetAndNumber basis:ancestor="generelInfo" contextRef="duration_only">Hvissingevej 10</gsd:AddressOfReportingEntityStreetAndNumber>
   <gsd:AddressOfReportingEntityPostcodeAndTown basis:ancestor="generelInfo" contextRef="duration_only">2600 Glostrup</gsd:AddressOfReportingEntityPostcodeAndTown>
   <gsd:TelephoneNumberOfReportingEntity basis:ancestor="generelInfo" contextRef="duration_only">43632010</gsd:TelephoneNumberOfReportingEntity>
   <gsd:IdentificationNumberCvrOfReportingEntity basis:ancestor="generelInfo" contextRef="duration_only">20378042</gsd:IdentificationNumberCvrOfReportingEntity>
   <gsd:ReportingPeriodStartDate basis:ancestor="generelInfo" contextRef="duration_only">2012-01-01</gsd:ReportingPeriodStartDate>
   <gsd:ReportingPeriodEndDate basis:ancestor="generelInfo" contextRef="duration_only">2012-12-31</gsd:ReportingPeriodEndDate>
   <sob:StatementByExecutiveAndSupervisoryBoards basis:ancestor="statementByExecutive" contextRef="duration_only">&lt;p xmlns="http://www.w3.org/1999/xhtml"&gt;Selskabets ledelse har dags dato aflagt årsrapporten for
2012 for Barney’s Malerfirma A/S.&lt;/p&gt;
&lt;p xmlns="http://www.w3.org/1999/xhtml"&gt; &lt;/p&gt;
&lt;p xmlns="http://www.w3.org/1999/xhtml"&gt;Årsrapporten er aflagt i overensstemmelse med
årsregnskabsloven. Det er ledelsens opfattelse, at
betingelserne for fravalg af revision er opfyldt.&lt;/p&gt;
&lt;p xmlns="http://www.w3.org/1999/xhtml"&gt; &lt;/p&gt;
&lt;p xmlns="http://www.w3.org/1999/xhtml"&gt;Vi anser den valgte regnskabspraksis for hensigtsmæssig,
således at årsrapporten giver et retvisende billede
af selskabets aktiver og passiver, finansielle stilling
samt resultatet.&lt;/p&gt;
&lt;p xmlns="http://www.w3.org/1999/xhtml"&gt; &lt;/p&gt;
&lt;p xmlns="http://www.w3.org/1999/xhtml"&gt;Årsrapporten indstilles til generalforsamlingens
godkendelse.&lt;/p&gt;
</sob:StatementByExecutiveAndSupervisoryBoards>
   <sob:PlaceOfSignatureOfStatement basis:ancestor="statementByExecutive" contextRef="duration_only">Glostrup</sob:PlaceOfSignatureOfStatement>
   <sob:DateOfApprovalOfAnnualReport basis:ancestor="statementByExecutive" contextRef="duration_only">2013-04-18</sob:DateOfApprovalOfAnnualReport>
   <cmn:NameAndSurnameOfMemberOfExecutiveBoard basis:ancestor="DetailsOnApprovalOfAnnualReportExecutiveAbstract"
                                               contextRef="duration_memberOfExecutiveBoardIdentifier_1">Kjeld Frode Baltsersen</cmn:NameAndSurnameOfMemberOfExecutiveBoard>
   <cmn:NameAndSurnameOfMemberOfSupervisoryBoard basis:ancestor="DetailsOnApprovalOfAnnualReportBoardAbstract"
                                                 contextRef="duration_memberOfSupervisoryBoardIdentifier_1">Susanne Baltsersen</cmn:NameAndSurnameOfMemberOfSupervisoryBoard>
   <cmn:NameAndSurnameOfMemberOfSupervisoryBoard basis:ancestor="DetailsOnApprovalOfAnnualReportBoardAbstract"
                                                 contextRef="duration_memberOfSupervisoryBoardIdentifier_2">Kjeld Frode Baltsersen</cmn:NameAndSurnameOfMemberOfSupervisoryBoard>
   <cmn:NameAndSurnameOfMemberOfSupervisoryBoard basis:ancestor="DetailsOnApprovalOfAnnualReportBoardAbstract"
                                                 contextRef="duration_memberOfSupervisoryBoardIdentifier_3">John Pedersen</cmn:NameAndSurnameOfMemberOfSupervisoryBoard>
   <arr:DescriptionOfOtherEngagement basis:ancestor="revision" contextRef="duration_only">Til ledelsen af Barney’s Malerfirma A/S
&lt;br xmlns="http://www.w3.org/1999/xhtml"/&gt;
&lt;br xmlns="http://www.w3.org/1999/xhtml"/&gt;Baseret på oplysninger fra virksomhedens ledelse har vi i overensstemmelse med den danske revisionsstandard om assistance med regnskabsopstilling opstillet virksomhedens årsrapport pr. 31. december 2012.
&lt;br xmlns="http://www.w3.org/1999/xhtml"/&gt;
&lt;br xmlns="http://www.w3.org/1999/xhtml"/&gt;Virksomhedens ledelse har ansvaret for årsrapporten. 
&lt;br xmlns="http://www.w3.org/1999/xhtml"/&gt;
&lt;br xmlns="http://www.w3.org/1999/xhtml"/&gt;Vi har ikke udført revision eller review og udtrykker derfor ikke nogen grad af sikkerhed om årsrapporten.</arr:DescriptionOfOtherEngagement>
   <arr:SignatureOfAuditorsPlace basis:ancestor="revision" contextRef="duration_only">Ballerup</arr:SignatureOfAuditorsPlace>
   <arr:SignatureOfAuditorsDate basis:ancestor="revision" contextRef="duration_only">2013-04-18</arr:SignatureOfAuditorsDate>
   <arr:NameAndSurnameOfAuditor basis:ancestor="DetailsOnSignatureAuditorsAbstract"
                                contextRef="duration_auditorIdentifier_1">Benny Klitbo</arr:NameAndSurnameOfAuditor>
   <arr:DescriptionOfAuditor basis:ancestor="DetailsOnSignatureAuditorsAbstract"
                             contextRef="duration_auditorIdentifier_1">Registreret revisor</arr:DescriptionOfAuditor>
   <arr:NameOfAuditFirm basis:ancestor="DetailsOnSignatureAuditorsAbstract"
                        contextRef="duration_auditorIdentifier_1">Multi revision ApS</arr:NameOfAuditFirm>
   <fsa:InformationOnReportingClassOfEntity basis:ancestor="regnskabspraksis" contextRef="duration_only">Årsrapporten er aflagt i overensstemmelse med årsregnskabslovens bestemmelser for Regnskabsklasse B.</fsa:InformationOnReportingClassOfEntity>
   <fsa:ClassOfReportingEntity basis:ancestor="regnskabspraksis" contextRef="duration_only">Regnskabsklasse B</fsa:ClassOfReportingEntity>
   <fsa:DisclosureOfAccountingPolicies basis:ancestor="regnskabspraksis" contextRef="duration_only">&lt;p xmlns="http://www.w3.org/1999/xhtml"&gt;Den anvendte regnskabspraksis er uændret i forhold til
sidste år.&lt;/p&gt;
&lt;p xmlns="http://www.w3.org/1999/xhtml"&gt; &lt;/p&gt;
&lt;p xmlns="http://www.w3.org/1999/xhtml"&gt;Generelt om indregning og måling
&lt;br/&gt; I resultatopgørelsen indregnes indtægter i takt
med, at de indtjenes. I resultatopgørelsen indregnes ligeledes
alle omkostninger, herunder afskrivninger og nedskrivninger.
&lt;br/&gt; Aktiver indregnes i balancen, når det er sandsynligt,
at fremtidige økonomiske fordele vil tilflyde selskabet, og
aktivets værdi kan måles pålideligt.
&lt;br/&gt; Forpligtelser indregnes i balancen, når det er
sandsynligt, at fremtidige økonomiske fordele vil fragå
selskabet, og forpligtelsens værdi kan måles
pålideligt.
&lt;br/&gt; Ved første indregning måles aktiver og
forpligtelser til kostpris. Efterfølgende måles aktiver
og forpligtelser som beskrevet for hver enkelt regnskabspost
nedenfor.&lt;/p&gt;
&lt;p xmlns="http://www.w3.org/1999/xhtml"&gt; &lt;/p&gt;
&lt;h2 xmlns="http://www.w3.org/1999/xhtml"&gt;Resultatopgørelse&lt;/h2&gt;
&lt;p xmlns="http://www.w3.org/1999/xhtml"&gt;Nettoomsætning
&lt;br/&gt; Nettoomsætningen indregnes i resultatopgørelsen,
såfremt levering og risikoovergang til køber har fundet
sted inden årets udgang.&lt;/p&gt;
&lt;p xmlns="http://www.w3.org/1999/xhtml"&gt; &lt;/p&gt;
&lt;p xmlns="http://www.w3.org/1999/xhtml"&gt;Andre eksterne omkostninger
&lt;br/&gt; Andre eksterne omkostninger omfatter omkostninger til
distribution, salg, reklame, administration, lokaler, tab på
debitorer, operationelle leasingomkostninger mv.&lt;/p&gt;
&lt;p xmlns="http://www.w3.org/1999/xhtml"&gt; &lt;/p&gt;
&lt;p xmlns="http://www.w3.org/1999/xhtml"&gt;Finansielle poster
&lt;br/&gt; Finansielle indtægter og omkostninger indregnes i
resultatopgørelsen med de beløb, der vedrører
regnskabsåret.&lt;/p&gt;
&lt;p xmlns="http://www.w3.org/1999/xhtml"&gt; &lt;/p&gt;
&lt;p xmlns="http://www.w3.org/1999/xhtml"&gt;Skat af årets resultat
&lt;br/&gt; Årets skat, som består af årets aktuelle skat
og forskydning i udskudt skat, indregnes i resultatopgørelsen
med den del, der kan henføres til årets resultat.&lt;/p&gt;
&lt;p xmlns="http://www.w3.org/1999/xhtml"&gt; &lt;/p&gt;
&lt;h2 xmlns="http://www.w3.org/1999/xhtml"&gt;Balance&lt;/h2&gt;
&lt;p xmlns="http://www.w3.org/1999/xhtml"&gt;Materielle anlægsaktiver
&lt;br/&gt; Andre anlæg, driftsmateriel og inventar måles til
kostpris med fradrag af akkumulerede afskrivninger.&lt;/p&gt;
&lt;p xmlns="http://www.w3.org/1999/xhtml"&gt;Afskrivningsgrundlaget er kostpris med fradrag af forventet
restværdi efter afsluttet brugstid. Der afskrives ikke på
grunde.&lt;/p&gt;
&lt;p xmlns="http://www.w3.org/1999/xhtml"&gt;Der foretages lineære afskrivninger baseret på en
vurdering af aktivernes forventede brugstid på 5 år.&lt;/p&gt;
&lt;p xmlns="http://www.w3.org/1999/xhtml"&gt;Fortjeneste eller tab ved afhændelse af materielle
anlægsaktiver opgøres som forskellen mellem salgspris med
fradrag af salgsomkostninger og den regnskabsmæssige
værdi på salgstidspunktet. Fortjeneste eller tab
indregnes i resultatopgørelsen under afskrivninger.&lt;/p&gt;
&lt;p xmlns="http://www.w3.org/1999/xhtml"&gt; &lt;/p&gt;
&lt;p xmlns="http://www.w3.org/1999/xhtml"&gt;Varebeholdninger og igangværende arbejder
&lt;br/&gt; Varebeholdninger måles til kostpris efter FIFO-metoden.
I tilfælde, hvor nettorealisationsværdien er lavere end
kostprisen, nedskrives til denne lavere værdi.&lt;/p&gt;
&lt;p xmlns="http://www.w3.org/1999/xhtml"&gt;Igangværende arbejder er opført til direkte løn-
og materialeudgifter med tillæg af andre direkte
produktionsomkostninger. Der er ved vurderingen indregnet en andel
af de på-regnede fortjenester på entreprisen.&lt;/p&gt;
&lt;p xmlns="http://www.w3.org/1999/xhtml"&gt; &lt;/p&gt;
</fsa:DisclosureOfAccountingPolicies>
   <fsa:GrossProfitLoss basis:ancestor="treeGroup2" contextRef="duration_only" decimals="0"
                        unitRef="DKK">2601232</fsa:GrossProfitLoss>
   <fsa:GrossProfitLoss basis:ancestor="treeGroup2" contextRef="duration_only_previous" decimals="0"
                        unitRef="DKK">2263</fsa:GrossProfitLoss>
   <fsa:DepreciationAmortisationExpenseAndImpairmentLossesOfPropertyPlantAndEquipmentAndIntangibleAssetsRecognisedInProfitOrLoss basis:ancestor="treeGroup3" contextRef="duration_only" decimals="0"
                                                                                                                                 unitRef="DKK">185558</fsa:DepreciationAmortisationExpenseAndImpairmentLossesOfPropertyPlantAndEquipmentAndIntangibleAssetsRecognisedInProfitOrLoss>
   <fsa:DepreciationAmortisationExpenseAndImpairmentLossesOfPropertyPlantAndEquipmentAndIntangibleAssetsRecognisedInProfitOrLoss basis:ancestor="treeGroup3" contextRef="duration_only_previous" decimals="0"
                                                                                                                                 unitRef="DKK">118</fsa:DepreciationAmortisationExpenseAndImpairmentLossesOfPropertyPlantAndEquipmentAndIntangibleAssetsRecognisedInProfitOrLoss>
   <fsa:ProfitLossFromOrdinaryOperatingActivities basis:ancestor="treeGroup3" contextRef="duration_only" decimals="0"
                                                  unitRef="DKK">2415674</fsa:ProfitLossFromOrdinaryOperatingActivities>
   <fsa:ProfitLossFromOrdinaryOperatingActivities basis:ancestor="treeGroup3" contextRef="duration_only_previous" decimals="0"
                                                  unitRef="DKK">2145</fsa:ProfitLossFromOrdinaryOperatingActivities>
   <fsa:OtherFinanceExpenses basis:ancestor="treeGroup4" contextRef="duration_only" decimals="0"
                             unitRef="DKK">11799</fsa:OtherFinanceExpenses>
   <fsa:OtherFinanceExpenses basis:ancestor="treeGroup4" contextRef="duration_only_previous" decimals="0"
                             unitRef="DKK">1</fsa:OtherFinanceExpenses>
   <fsa:ProfitLossFromOrdinaryActivitiesBeforeTax basis:ancestor="treeGroup4" contextRef="duration_only" decimals="0"
                                                  unitRef="DKK">2403875</fsa:ProfitLossFromOrdinaryActivitiesBeforeTax>
   <fsa:ProfitLossFromOrdinaryActivitiesBeforeTax basis:ancestor="treeGroup4" contextRef="duration_only_previous" decimals="0"
                                                  unitRef="DKK">2144</fsa:ProfitLossFromOrdinaryActivitiesBeforeTax>
   <fsa:ExtraordinaryProfitLossBeforeTax basis:ancestor="treeGroup6" contextRef="duration_only" decimals="0"
                                         unitRef="DKK">2403875</fsa:ExtraordinaryProfitLossBeforeTax>
   <fsa:ExtraordinaryProfitLossBeforeTax basis:ancestor="treeGroup6" contextRef="duration_only_previous" decimals="0"
                                         unitRef="DKK">2144</fsa:ExtraordinaryProfitLossBeforeTax>
   <fsa:TaxExpense basis:ancestor="treeGroup6" contextRef="duration_only" decimals="0"
                   unitRef="DKK">609675</fsa:TaxExpense>
   <fsa:TaxExpense basis:ancestor="treeGroup6" contextRef="duration_only_previous" decimals="0"
                   unitRef="DKK">544</fsa:TaxExpense>
   <fsa:ProfitLoss basis:ancestor="treeGroup7" contextRef="duration_only" decimals="0"
                   unitRef="DKK">1794200</fsa:ProfitLoss>
   <fsa:ProfitLoss basis:ancestor="treeGroup7" contextRef="duration_only_previous" decimals="0"
                   unitRef="DKK">1600</fsa:ProfitLoss>
   <fsa:ProfitLoss basis:ancestor="treeGroup8"
                   contextRef="duration_ProposedDividendRecognisedInEquityMember"
                   decimals="0"
                   unitRef="DKK">1800000</fsa:ProfitLoss>
   <fsa:ProfitLoss basis:ancestor="treeGroup8"
                   contextRef="duration_ProposedDividendRecognisedInEquityMember_previous"
                   decimals="0"
                   unitRef="DKK">1600</fsa:ProfitLoss>
   <fsa:ProfitLoss basis:ancestor="treeGroup8" contextRef="duration_RetainedEarningsMember"
                   decimals="0"
                   unitRef="DKK">-5800</fsa:ProfitLoss>
   <fsa:ProfitLoss basis:ancestor="treeGroup8"
                   contextRef="duration_RetainedEarningsMember_previous"
                   decimals="0"
                   unitRef="DKK">0</fsa:ProfitLoss>
   <fsa:ProfitLoss basis:ancestor="treeGroup8" contextRef="duration_only" decimals="0"
                   unitRef="DKK">1794200</fsa:ProfitLoss>
   <fsa:ProfitLoss basis:ancestor="treeGroup8" contextRef="duration_only_previous" decimals="0"
                   unitRef="DKK">1600</fsa:ProfitLoss>
   <fsa:FixturesFittingsToolsAndEquipment basis:ancestor="treeGroup2" contextRef="instant_only" decimals="0"
                                          unitRef="DKK">525492</fsa:FixturesFittingsToolsAndEquipment>
   <fsa:FixturesFittingsToolsAndEquipment basis:ancestor="treeGroup2" contextRef="instant_only_previous" decimals="0"
                                          unitRef="DKK">372</fsa:FixturesFittingsToolsAndEquipment>
   <fsa:PropertyPlantAndEquipment basis:ancestor="treeGroup2" contextRef="instant_only" decimals="0"
                                  unitRef="DKK">525492</fsa:PropertyPlantAndEquipment>
   <fsa:PropertyPlantAndEquipment basis:ancestor="treeGroup2" contextRef="instant_only_previous" decimals="0"
                                  unitRef="DKK">372</fsa:PropertyPlantAndEquipment>
   <fsa:NoncurrentAssets basis:ancestor="treeGroup4" contextRef="instant_only" decimals="0"
                         unitRef="DKK">525492</fsa:NoncurrentAssets>
   <fsa:NoncurrentAssets basis:ancestor="treeGroup4" contextRef="instant_only_previous" decimals="0"
                         unitRef="DKK">372</fsa:NoncurrentAssets>
   <fsa:RawMaterialsAndConsumables basis:ancestor="treeGroup5" contextRef="instant_only" decimals="0"
                                   unitRef="DKK">10000</fsa:RawMaterialsAndConsumables>
   <fsa:RawMaterialsAndConsumables basis:ancestor="treeGroup5" contextRef="instant_only_previous" decimals="0"
                                   unitRef="DKK">10</fsa:RawMaterialsAndConsumables>
   <fsa:Inventories basis:ancestor="treeGroup5" contextRef="instant_only" decimals="0"
                    unitRef="DKK">10000</fsa:Inventories>
   <fsa:Inventories basis:ancestor="treeGroup5" contextRef="instant_only_previous" decimals="0"
                    unitRef="DKK">10</fsa:Inventories>
   <fsa:ShorttermTradeReceivables basis:ancestor="treeGroup6" contextRef="instant_only" decimals="0"
                                  unitRef="DKK">2892039</fsa:ShorttermTradeReceivables>
   <fsa:ShorttermTradeReceivables basis:ancestor="treeGroup6" contextRef="instant_only_previous" decimals="0"
                                  unitRef="DKK">3049</fsa:ShorttermTradeReceivables>
   <fsa:ContractWorkInProgress basis:ancestor="treeGroup6" contextRef="instant_only" decimals="0"
                               unitRef="DKK">500000</fsa:ContractWorkInProgress>
   <fsa:ContractWorkInProgress basis:ancestor="treeGroup6" contextRef="instant_only_previous" decimals="0"
                               unitRef="DKK">500</fsa:ContractWorkInProgress>
   <fsa:OtherShorttermReceivables basis:ancestor="treeGroup6" contextRef="instant_only" decimals="0"
                                  unitRef="DKK">670000</fsa:OtherShorttermReceivables>
   <fsa:OtherShorttermReceivables basis:ancestor="treeGroup6" contextRef="instant_only_previous" decimals="0"
                                  unitRef="DKK">170</fsa:OtherShorttermReceivables>
   <fsa:ShorttermReceivables basis:ancestor="treeGroup6" contextRef="instant_only" decimals="0"
                             unitRef="DKK">4062039</fsa:ShorttermReceivables>
   <fsa:ShorttermReceivables basis:ancestor="treeGroup6" contextRef="instant_only_previous" decimals="0"
                             unitRef="DKK">3719</fsa:ShorttermReceivables>
   <fsa:OtherShorttermInvestments basis:ancestor="treeGroup7" contextRef="instant_only" decimals="0"
                                  unitRef="DKK">66366</fsa:OtherShorttermInvestments>
   <fsa:OtherShorttermInvestments basis:ancestor="treeGroup7" contextRef="instant_only_previous" decimals="0"
                                  unitRef="DKK">66</fsa:OtherShorttermInvestments>
   <fsa:ShorttermInvestments basis:ancestor="treeGroup7" contextRef="instant_only" decimals="0"
                             unitRef="DKK">66366</fsa:ShorttermInvestments>
   <fsa:ShorttermInvestments basis:ancestor="treeGroup7" contextRef="instant_only_previous" decimals="0"
                             unitRef="DKK">66</fsa:ShorttermInvestments>
   <fsa:CashAndCashEquivalents basis:ancestor="treeGroup8" contextRef="instant_only" decimals="0"
                               unitRef="DKK">627389</fsa:CashAndCashEquivalents>
   <fsa:CashAndCashEquivalents basis:ancestor="treeGroup8" contextRef="instant_only_previous" decimals="0"
                               unitRef="DKK">1723</fsa:CashAndCashEquivalents>
   <fsa:CurrentAssets basis:ancestor="treeGroup9" contextRef="instant_only" decimals="0"
                      unitRef="DKK">4765794</fsa:CurrentAssets>
   <fsa:CurrentAssets basis:ancestor="treeGroup9" contextRef="instant_only_previous" decimals="0"
                      unitRef="DKK">5518</fsa:CurrentAssets>
   <fsa:Assets basis:ancestor="treeGroup10" contextRef="instant_only" decimals="0"
               unitRef="DKK">5291286</fsa:Assets>
   <fsa:Assets basis:ancestor="treeGroup10" contextRef="instant_only_previous" decimals="0"
               unitRef="DKK">5890</fsa:Assets>
   <fsa:ContributedCapital basis:ancestor="treeGroup1" contextRef="instant_only" decimals="0"
                           unitRef="DKK">500000</fsa:ContributedCapital>
   <fsa:ContributedCapital basis:ancestor="treeGroup1" contextRef="instant_only_previous" decimals="0"
                           unitRef="DKK">500</fsa:ContributedCapital>
   <fsa:RetainedEarnings basis:ancestor="treeGroup1" contextRef="instant_only" decimals="0"
                         unitRef="DKK">852667</fsa:RetainedEarnings>
   <fsa:RetainedEarnings basis:ancestor="treeGroup1" contextRef="instant_only_previous" decimals="0"
                         unitRef="DKK">858</fsa:RetainedEarnings>
   <fsa:ProposedDividendRecognisedInEquity basis:ancestor="treeGroup1" contextRef="instant_only" decimals="0"
                                           unitRef="DKK">1800000</fsa:ProposedDividendRecognisedInEquity>
   <fsa:ProposedDividendRecognisedInEquity basis:ancestor="treeGroup1" contextRef="instant_only_previous" decimals="0"
                                           unitRef="DKK">1600</fsa:ProposedDividendRecognisedInEquity>
   <fsa:Equity basis:ancestor="treeGroup1" contextRef="instant_only" decimals="0"
               unitRef="DKK">3152667</fsa:Equity>
   <fsa:Equity basis:ancestor="treeGroup1" contextRef="instant_only_previous" decimals="0"
               unitRef="DKK">2958</fsa:Equity>
   <fsa:ShorttermTradePayables basis:ancestor="treeGroup4" contextRef="instant_only" decimals="0"
                               unitRef="DKK">101212</fsa:ShorttermTradePayables>
   <fsa:ShorttermTradePayables basis:ancestor="treeGroup4" contextRef="instant_only_previous" decimals="0"
                               unitRef="DKK">71</fsa:ShorttermTradePayables>
   <fsa:OtherShorttermPayables basis:ancestor="treeGroup4" contextRef="instant_only" decimals="0"
                               unitRef="DKK">2037407</fsa:OtherShorttermPayables>
   <fsa:OtherShorttermPayables basis:ancestor="treeGroup4" contextRef="instant_only_previous" decimals="0"
                               unitRef="DKK">2861</fsa:OtherShorttermPayables>
   <fsa:ShorttermLiabilitiesOtherThanProvisions basis:ancestor="treeGroup4" contextRef="instant_only" decimals="0"
                                                unitRef="DKK">2138619</fsa:ShorttermLiabilitiesOtherThanProvisions>
   <fsa:ShorttermLiabilitiesOtherThanProvisions basis:ancestor="treeGroup4" contextRef="instant_only_previous" decimals="0"
                                                unitRef="DKK">2932</fsa:ShorttermLiabilitiesOtherThanProvisions>
   <fsa:LiabilitiesOtherThanProvisions basis:ancestor="treeGroup5" contextRef="instant_only" decimals="0"
                                       unitRef="DKK">2138619</fsa:LiabilitiesOtherThanProvisions>
   <fsa:LiabilitiesOtherThanProvisions basis:ancestor="treeGroup5" contextRef="instant_only_previous" decimals="0"
                                       unitRef="DKK">2932</fsa:LiabilitiesOtherThanProvisions>
   <fsa:LiabilitiesAndEquity basis:ancestor="treeGroup6" contextRef="instant_only" decimals="0"
                             unitRef="DKK">5291286</fsa:LiabilitiesAndEquity>
   <fsa:LiabilitiesAndEquity basis:ancestor="treeGroup6" contextRef="instant_only_previous" decimals="0"
                             unitRef="DKK">5890</fsa:LiabilitiesAndEquity>
   <fsa:DisclosureOfPropertyPlantAndEquipment basis:ancestor="treeGroup2" contextRef="duration_only">
&lt;table xmlns="http://www.w3.org/1999/xhtml" style="border-bottom: 0pt; border-left: 0pt; width: 650px; border-collapse: collapse; border-top: 0pt; border-right: 0pt"&gt;
  &lt;tbody&gt;
    &lt;tr&gt;
      &lt;th style="border-bottom: 0pt; border-left: 0pt; width: 55%; border-top: 0pt; border-right: 0pt"&gt; &lt;/th&gt;
      &lt;th style="border-bottom: 0pt; text-align: right; border-left: 0pt; width: 15%; border-top: 0pt; font-weight: bold; border-right: 0pt"&gt;Andre
      Anlæg mv.&lt;/th&gt;
    &lt;/tr&gt;
    &lt;tr&gt;
      &lt;th&gt; &lt;/th&gt;
      &lt;th style="border-bottom: 1px solid; text-align: right; padding-bottom: 10px"&gt;kr.&lt;/th&gt;
    &lt;/tr&gt;
    &lt;tr&gt;
      &lt;td&gt;Kostpris primo&lt;/td&gt;
      &lt;td style="text-align: right"&gt;2.002.735&lt;/td&gt;
    &lt;/tr&gt;
    &lt;tr&gt;
      &lt;td&gt;Tilgang&lt;/td&gt;
      &lt;td style="text-align: right"&gt;338.600&lt;/td&gt;
    &lt;/tr&gt;
    &lt;tr&gt;
      &lt;td&gt;Afgang&lt;/td&gt;
      &lt;td style="text-align: right"&gt;0&lt;/td&gt;
    &lt;/tr&gt;
    &lt;tr&gt;
      &lt;td style="font-weight: bold"&gt;Kostpris ultimo&lt;/td&gt;
      &lt;td style="border-bottom: 2px solid; text-align: right; border-top: 2px solid; font-weight: bold"&gt;2.341.335&lt;/td&gt;
    &lt;/tr&gt;
    &lt;tr&gt;
      &lt;td&gt; &lt;/td&gt;
      &lt;td style="text-align: right"&gt; &lt;/td&gt;
    &lt;/tr&gt;
    &lt;tr&gt;
      &lt;td&gt;Af- og nedskrivning primo&lt;/td&gt;
      &lt;td style="text-align: right"&gt;1.630.285&lt;/td&gt;
    &lt;/tr&gt;
    &lt;tr&gt;
      &lt;td&gt;Årets afskrivning&lt;/td&gt;
      &lt;td style="text-align: right"&gt;185.558&lt;/td&gt;
    &lt;/tr&gt;
    &lt;tr&gt;
      &lt;td&gt;Tilbageførsel ved afgang&lt;/td&gt;
      &lt;td style="text-align: right"&gt;0&lt;/td&gt;
    &lt;/tr&gt;
    &lt;tr&gt;
      &lt;td style="font-weight: bold"&gt;Af- og nedskrivning ultimo&lt;/td&gt;
      &lt;td style="border-bottom: 2px solid; text-align: right; border-top: 2px solid; font-weight: bold"&gt;1.815.843&lt;/td&gt;
    &lt;/tr&gt;
    &lt;tr&gt;
      &lt;td&gt; &lt;/td&gt;
      &lt;td style="text-align: right"&gt; &lt;/td&gt;
    &lt;/tr&gt;
    &lt;tr&gt;
      &lt;td style="font-weight: bold"&gt;Regnskabsmæssig værdi
      ultimo&lt;/td&gt;
      &lt;td style="border-bottom: 1px solid; text-align: right; font-weight: bold"&gt;525.492&lt;/td&gt;
    &lt;/tr&gt;
    &lt;tr&gt;
      &lt;td/&gt;
    &lt;/tr&gt;
  &lt;/tbody&gt;
&lt;/table&gt;
</fsa:DisclosureOfPropertyPlantAndEquipment>
   <fsa:DisclosureOfEquity basis:ancestor="treeGroup1" contextRef="duration_only">
&lt;table xmlns="http://www.w3.org/1999/xhtml" style="border-bottom: 0pt; border-left: 0pt; width: 650px; border-collapse: collapse; border-top: 0pt; border-right: 0pt"&gt;
  &lt;tbody&gt;
    &lt;tr&gt;
      &lt;th style="border-bottom: 0pt; border-left: 0pt; width: 30%; border-top: 0pt; border-right: 0pt"&gt; &lt;/th&gt;
      &lt;th style="border-bottom: 0pt; text-align: right; border-left: 0pt; width: 14%; border-top: 0pt; font-weight: bold; border-right: 0pt"&gt;Virksomheds-kapital&lt;/th&gt;
      &lt;th style="border-bottom: 0pt; text-align: right; border-left: 0pt; width: 14%; border-top: 0pt; font-weight: bold; border-right: 0pt"&gt;Overført
      resultat&lt;/th&gt;
      &lt;th style="border-bottom: 0pt; text-align: right; border-left: 0pt; width: 14%; border-top: 0pt; font-weight: bold; border-right: 0pt"&gt;Foreslået
      udbytte&lt;/th&gt;
      &lt;th style="border-bottom: 0pt; text-align: right; border-left: 0pt; width: 14%; border-top: 0pt; font-weight: bold; border-right: 0pt"&gt;Ialt&lt;/th&gt;
    &lt;/tr&gt;
    &lt;tr&gt;
      &lt;th style="border-bottom: 0pt; border-left: 0pt; width: 30%; border-top: 0pt; border-right: 0pt"&gt; &lt;/th&gt;
      &lt;th style="border-bottom: 0pt; text-align: right; border-left: 0pt; width: 14%; border-top: 0pt; font-weight: bold; border-right: 0pt"&gt;kr.&lt;/th&gt;
      &lt;th style="border-bottom: 0pt; text-align: right; border-left: 0pt; width: 14%; border-top: 0pt; font-weight: bold; border-right: 0pt"&gt;kr.&lt;/th&gt;
      &lt;th style="border-bottom: 0pt; text-align: right; border-left: 0pt; width: 14%; border-top: 0pt; font-weight: bold; border-right: 0pt"&gt;kr.&lt;/th&gt;
      &lt;th style="border-bottom: 0pt; text-align: right; border-left: 0pt; width: 14%; border-top: 0pt; font-weight: bold; border-right: 0pt"&gt;kr.&lt;/th&gt;
    &lt;/tr&gt;
    &lt;tr&gt;
      &lt;td&gt;Saldo primo&lt;/td&gt;
      &lt;td style="text-align: right"&gt;500.000&lt;/td&gt;
      &lt;td style="text-align: right"&gt;858.467&lt;/td&gt;
      &lt;td style="text-align: right"&gt;1.600.000&lt;/td&gt;
      &lt;td style="text-align: right"&gt;2.958.467&lt;/td&gt;
    &lt;/tr&gt;
    &lt;tr&gt;
      &lt;td&gt;Udloddet ordinært udbytte&lt;/td&gt;
      &lt;td style="text-align: right"&gt;0&lt;/td&gt;
      &lt;td style="text-align: right"&gt;0&lt;/td&gt;
      &lt;td style="text-align: right"&gt;-1.600.000&lt;/td&gt;
      &lt;td style="text-align: right"&gt;-1.600.000&lt;/td&gt;
    &lt;/tr&gt;
    &lt;tr&gt;
      &lt;td&gt;Årets resultat&lt;/td&gt;
      &lt;td style="text-align: right"&gt;0&lt;/td&gt;
      &lt;td style="text-align: right"&gt;-5.800&lt;/td&gt;
      &lt;td style="text-align: right"&gt;1.800.000&lt;/td&gt;
      &lt;td style="text-align: right"&gt;1.794.200&lt;/td&gt;
    &lt;/tr&gt;
    &lt;tr&gt;
      &lt;td style="font-weight: bold"&gt;Egenkapital ultimo&lt;/td&gt;
      &lt;td style="border-bottom: 2px solid; text-align: right; border-top: 2px solid; font-weight: bold"&gt;500.000&lt;/td&gt;
      &lt;td style="border-bottom: 2px solid; text-align: right; border-top: 2px solid; font-weight: bold"&gt;852.667&lt;/td&gt;
      &lt;td style="border-bottom: 2px solid; text-align: right; border-top: 2px solid; font-weight: bold"&gt;1.800.000&lt;/td&gt;
      &lt;td style="border-bottom: 2px solid; text-align: right; border-top: 2px solid; font-weight: bold"&gt;3.152.667&lt;/td&gt;
    &lt;/tr&gt;
  &lt;/tbody&gt;
&lt;/table&gt;
&lt;p xmlns="http://www.w3.org/1999/xhtml"&gt; &lt;/p&gt;
</fsa:DisclosureOfEquity>
   <gsd:NameOfSubmittingEnterprise basis:ancestor="generelInfo" contextRef="duration_only">Multi Revision ApS</gsd:NameOfSubmittingEnterprise>
   <gsd:AddressOfSubmittingEnterpriseStreetAndNumber basis:ancestor="generelInfo" contextRef="duration_only">Postbox 86</gsd:AddressOfSubmittingEnterpriseStreetAndNumber>
   <gsd:AddressOfSubmittingEnterprisePostcodeAndTown basis:ancestor="generelInfo" contextRef="duration_only">2750 Ballerup</gsd:AddressOfSubmittingEnterprisePostcodeAndTown>
</xbrli:xbrl>