<?xml version="1.0" encoding="utf-8"?>
<!--Dette XBRL instansdokument er genereret af IT Revisor (5.5.5.0) - http://www.focus-it.dk/it-revisor.aspx-->
<xbrl xmlns="http://www.xbrl.org/2003/instance" xmlns:mrv="http://xbrl.dcca.dk/mrv" xmlns:arr="http://xbrl.dcca.dk/arr" xmlns:fsa="http://xbrl.dcca.dk/fsa" xmlns:sob="http://xbrl.dcca.dk/sob" xmlns:gsd="http://xbrl.dcca.dk/gsd" xmlns:tax="http://xbrl.dcca.dk/tax" xmlns:dst="http://xbrl.dcca.dk/dst" xmlns:cmn="http://xbrl.dcca.dk/cmn" xmlns:eogs="http://xbrl.dcca.dk/eogs" xmlns:iso4217="http://www.xbrl.org/2003/iso4217" xmlns:xlink="http://www.w3.org/1999/xlink" xmlns:link="http://www.xbrl.org/2003/linkbase" xmlns:xbrldi="http://xbrl.org/2006/xbrldi">
  <link:schemaRef xlink:type="simple" xlink:href="http://archprod.service.eogs.dk/taxonomy/20130401/entryDanishGAAPBalanceSheetReportFormIncomeStatementByNatureIncludingManagementsReviewStatisticsAndTax20130401.xsd" />
  <context id="Per01072013_30062014">
    <entity>
      <identifier scheme="http://www.dcca.dk/cvr">27289460</identifier>
    </entity>
    <period>
      <startDate>2013-07-01</startDate>
      <endDate>2014-06-30</endDate>
    </period>
  </context>
  <context id="Per01072012_30062013">
    <entity>
      <identifier scheme="http://www.dcca.dk/cvr">27289460</identifier>
    </entity>
    <period>
      <startDate>2012-07-01</startDate>
      <endDate>2013-06-30</endDate>
    </period>
  </context>
  <context id="Per01072013_30062014-Instant">
    <entity>
      <identifier scheme="http://www.dcca.dk/cvr">27289460</identifier>
    </entity>
    <period>
      <instant>2014-06-30</instant>
    </period>
  </context>
  <context id="Per01072012_30062013-Instant">
    <entity>
      <identifier scheme="http://www.dcca.dk/cvr">27289460</identifier>
    </entity>
    <period>
      <instant>2013-06-30</instant>
    </period>
  </context>
  <context id="Per01072013_30062014_0_Identifikation_af_medlem_af_direktionen">
    <entity>
      <identifier scheme="http://www.dcca.dk/cvr">27289460</identifier>
    </entity>
    <period>
      <startDate>2013-07-01</startDate>
      <endDate>2014-06-30</endDate>
    </period>
    <scenario>
      <xbrldi:typedMember dimension="cmn:IdentificationOfMemberOfExecutiveBoardDimension">
        <cmn:memberOfBoardIdentifier>0</cmn:memberOfBoardIdentifier>
      </xbrldi:typedMember>
    </scenario>
  </context>
  <context id="Per01072013_30062014_1_Identifikation_af_medlem_af_bestyrelsen">
    <entity>
      <identifier scheme="http://www.dcca.dk/cvr">27289460</identifier>
    </entity>
    <period>
      <startDate>2013-07-01</startDate>
      <endDate>2014-06-30</endDate>
    </period>
    <scenario>
      <xbrldi:typedMember dimension="cmn:IdentificationOfMemberOfSupervisoryBoardDimension">
        <cmn:memberOfBoardIdentifier>1</cmn:memberOfBoardIdentifier>
      </xbrldi:typedMember>
    </scenario>
  </context>
  <context id="Per01072013_30062014_2_Identifikation_af_medlem_af_bestyrelsen">
    <entity>
      <identifier scheme="http://www.dcca.dk/cvr">27289460</identifier>
    </entity>
    <period>
      <startDate>2013-07-01</startDate>
      <endDate>2014-06-30</endDate>
    </period>
    <scenario>
      <xbrldi:typedMember dimension="cmn:IdentificationOfMemberOfSupervisoryBoardDimension">
        <cmn:memberOfBoardIdentifier>2</cmn:memberOfBoardIdentifier>
      </xbrldi:typedMember>
    </scenario>
  </context>
  <context id="Per01072013_30062014_3_Identifikation_af_revisor">
    <entity>
      <identifier scheme="http://www.dcca.dk/cvr">27289460</identifier>
    </entity>
    <period>
      <startDate>2013-07-01</startDate>
      <endDate>2014-06-30</endDate>
    </period>
    <scenario>
      <xbrldi:typedMember dimension="cmn:IdentificationOfAuditorDimension">
        <cmn:auditorIdentifier>3</cmn:auditorIdentifier>
      </xbrldi:typedMember>
    </scenario>
  </context>
  <context id="Per01072013_30062014_4_Overført_resultat">
    <entity>
      <identifier scheme="http://www.dcca.dk/cvr">27289460</identifier>
    </entity>
    <period>
      <startDate>2013-07-01</startDate>
      <endDate>2014-06-30</endDate>
    </period>
    <scenario>
      <xbrldi:explicitMember dimension="fsa:ResultDistributionDimension">fsa:RetainedEarningsMember</xbrldi:explicitMember>
    </scenario>
  </context>
  <context id="Per01072012_30062013_0_Overført_resultat">
    <entity>
      <identifier scheme="http://www.dcca.dk/cvr">27289460</identifier>
    </entity>
    <period>
      <startDate>2012-07-01</startDate>
      <endDate>2013-06-30</endDate>
    </period>
    <scenario>
      <xbrldi:explicitMember dimension="fsa:ResultDistributionDimension">fsa:RetainedEarningsMember</xbrldi:explicitMember>
    </scenario>
  </context>
  <unit id="DKK">
    <measure>iso4217:DKK</measure>
  </unit>
  <unit id="shares">
    <measure>shares</measure>
  </unit>
  <unit id="pure">
    <measure>pure</measure>
  </unit>
  <gsd:DateOfGeneralMeeting contextRef="Per01072013_30062014">2014-11-28</gsd:DateOfGeneralMeeting>
  <gsd:NameAndSurnameOfChairmanOfGeneralMeeting contextRef="Per01072013_30062014">Dennis Jacobsen</gsd:NameAndSurnameOfChairmanOfGeneralMeeting>
  <arr:SignatureOfAuditorsPlace contextRef="Per01072013_30062014">Køge</arr:SignatureOfAuditorsPlace>
  <arr:SignatureOfAuditorsDate contextRef="Per01072013_30062014">2014-11-27</arr:SignatureOfAuditorsDate>
  <sob:PlaceOfSignatureOfStatement contextRef="Per01072013_30062014">Klippinge</sob:PlaceOfSignatureOfStatement>
  <sob:DateOfApprovalOfAnnualReport contextRef="Per01072013_30062014">2014-11-27</sob:DateOfApprovalOfAnnualReport>
  <fsa:ClassOfReportingEntity contextRef="Per01072013_30062014">Regnskabsklasse B</fsa:ClassOfReportingEntity>
  <fsa:SelectedElementsFromReportingClassC contextRef="Per01072013_30062014">false</fsa:SelectedElementsFromReportingClassC>
  <fsa:SelectedElementsFromReportingClassD contextRef="Per01072013_30062014">false</fsa:SelectedElementsFromReportingClassD>
  <cmn:TypeOfAuditorAssistance contextRef="Per01072013_30062014">Revisionspåtegning</cmn:TypeOfAuditorAssistance>
  <gsd:InformationOnTypeOfSubmittedReport contextRef="Per01072013_30062014">Årsrapport</gsd:InformationOnTypeOfSubmittedReport>
  <gsd:IdentificationNumberCvrOfReportingEntity contextRef="Per01072013_30062014">27289460</gsd:IdentificationNumberCvrOfReportingEntity>
  <gsd:NameOfReportingEntity contextRef="Per01072013_30062014">Jens Jacobsen Byg A/S</gsd:NameOfReportingEntity>
  <gsd:AddressOfReportingEntityStreetName contextRef="Per01072013_30062014">Borgergade 12</gsd:AddressOfReportingEntityStreetName>
  <gsd:AddressOfReportingEntityPostCodeIdentifier contextRef="Per01072013_30062014">4672</gsd:AddressOfReportingEntityPostCodeIdentifier>
  <gsd:AddressOfReportingEntityDistrictName contextRef="Per01072013_30062014">Klippinge</gsd:AddressOfReportingEntityDistrictName>
  <gsd:RegisteredOfficeOfReportingEntity contextRef="Per01072013_30062014">Stevns Kommune</gsd:RegisteredOfficeOfReportingEntity>
  <gsd:TelephoneNumberOfReportingEntity contextRef="Per01072013_30062014">20128418</gsd:TelephoneNumberOfReportingEntity>
  <gsd:EmailOfReportingEntity contextRef="Per01072013_30062014">dennis@jjbas.dk</gsd:EmailOfReportingEntity>
  <gsd:ReportingPeriodStartDate contextRef="Per01072013_30062014">2013-07-01</gsd:ReportingPeriodStartDate>
  <gsd:ReportingPeriodEndDate contextRef="Per01072013_30062014">2014-06-30</gsd:ReportingPeriodEndDate>
  <gsd:NameOfSubmittingEnterprise contextRef="Per01072013_30062014">Wind Revision, Registreret Revisionsanpartsselskab</gsd:NameOfSubmittingEnterprise>
  <gsd:AddressOfSubmittingEnterpriseStreetAndNumber contextRef="Per01072013_30062014">Søndre Alle 43 C</gsd:AddressOfSubmittingEnterpriseStreetAndNumber>
  <gsd:AddressOfSubmittingEnterprisePostcodeAndTown contextRef="Per01072013_30062014">4600, Køge</gsd:AddressOfSubmittingEnterprisePostcodeAndTown>
  <sob:IdentificationOfApprovedAnnualReport contextRef="Per01072013_30062014">Bestyrelsen og direktionen har dags dato behandlet og godkendt årsrapporten for perioden 1. juli 2013 - 30. juni 2014 for Jens Jacobsen Byg A/S.</sob:IdentificationOfApprovedAnnualReport>
  <sob:ConfirmationThatAnnualReportIsPresentedInAccordanceWithRequirementsProvidedForByLegislationAnyStandardsAndRequirementsProvidedByArticlesOfAssociationOrByAgreement contextRef="Per01072013_30062014">Årsrapporten aflægges i overensstemmelse med årsregnskabsloven.</sob:ConfirmationThatAnnualReportIsPresentedInAccordanceWithRequirementsProvidedForByLegislationAnyStandardsAndRequirementsProvidedByArticlesOfAssociationOrByAgreement>
  <sob:ConfirmationThatFinancialStatementGivesTrueAndFairViewOfAssetsLiabilitiesEquityFinancialPositionAndResults contextRef="Per01072013_30062014">Det er vores opfattelse, at årsregnskabet giver et retvisende billede af selskabets aktiver, passiver og finansielle stilling pr. 30. juni 2014 samt af resultatet af selskabets aktiviteter for perioden 1. juli 2013 - 30. juni 2014.</sob:ConfirmationThatFinancialStatementGivesTrueAndFairViewOfAssetsLiabilitiesEquityFinancialPositionAndResults>
  <sob:ManagementsStatementAboutManagementsReview contextRef="Per01072013_30062014">Ledelsesberetningen indeholder efter vores opfattelse en retvisende redegørelse for de forhold, beretningen omhandler.</sob:ManagementsStatementAboutManagementsReview>
  <sob:RecommendationForApprovalOfAnnualReportByGeneralMeeting contextRef="Per01072013_30062014">Årsrapporten indstilles til generalforsamlingens godkendelse.</sob:RecommendationForApprovalOfAnnualReportByGeneralMeeting>
  <arr:AddresseeOfAuditorsReportOnReviewOfFinancialStatements contextRef="Per01072013_30062014">Til kapitalejerne af Jens Jacobsen Byg A/S</arr:AddresseeOfAuditorsReportOnReviewOfFinancialStatements>
  <arr:IdentificationOfAuditedFinancialStatements contextRef="Per01072013_30062014">Vi har revideret årsregnskabet for Jens Jacobsen Byg A/S for perioden 1. juli 2013 - 30. juni 2014, der omfatter anvendt regnskabspraksis, resultatopgørelse, balance og noter. Årsregnskabet udarbejdes efter årsregnskabsloven.</arr:IdentificationOfAuditedFinancialStatements>
  <arr:StatementOfExecutiveAndSupervisoryBoardsResponsibilityForFinancialStatements contextRef="Per01072013_30062014">Ledelsens ansvar for årsregnskabet&lt;br xmlns="http://www.w3.org/1999/xhtml"/&gt;Selskabets ledelse har ansvaret for udarbejdelsen af et årsregnskab, der giver et retvisende billede i overensstemmelse med årsregnskabsloven. Ledelsen har endvidere ansvaret for den interne kontrol, som ledelsen anser nødvendig for at udarbejde et årsregnskab uden væsentlig fejlinformation, uanset om denne skyldes besvigelser eller fejl.</arr:StatementOfExecutiveAndSupervisoryBoardsResponsibilityForFinancialStatements>
  <arr:StatementOfAuditorsResponsibilityForAuditAndAuditPerformed contextRef="Per01072013_30062014">Revisors ansvar&lt;br xmlns="http://www.w3.org/1999/xhtml"/&gt;Vores ansvar er at udtrykke en konklusion om årsregnskabet på grundlag af vores revision. Vi har udført revisionen i overensstemmelse med internationale standarder om revision og yderligere krav ifølge dansk revisorlovgivning. Dette kræver, at vi overholder etiske krav samt planlægger og udfører revisionen for at opnå høj grad af sikkerhed for, om årsregnskabet er uden væsentlig fejlinformation.En revision omfatter udførelse af revisionshandlinger for at opnå revisionsbevis for beløb og oplysninger i årsregnskabet. De valgte revisionshandlinger afhænger af revisors vurdering, herunder vurdering af risici for væsentlig fejlinformation i årsregnskabet, uanset om denne skyldes besvigelser eller fejl. Ved risikovurderingen overvejer revisor intern kontrol, der er relevant for selskabets udarbejdelse af et årsregnskab, der giver et retvisende billede. Formålet hermed er at udforme revisionshandlinger, der er passende efter omstændighederne, men ikke at udtrykke en konklusion om effektiviteten af selskabets interne kontrol. En revision omfatter endvidere vurdering af, om ledelsens valg af regnskabspraksis er passende, om ledelsens regnskabsmæssige skøn er rimelige samt den samlede præsentation af årsregnskabet.&lt;br xmlns="http://www.w3.org/1999/xhtml"/&gt;Det er vores opfattelse, at det opnåede revisionsbevis er tilstrækkeligt og egnet som grundlag for vor konklusion.Revisionen har ikke givet anledning til forbehold.</arr:StatementOfAuditorsResponsibilityForAuditAndAuditPerformed>
  <arr:OpinionOnAuditedFinancialStatements contextRef="Per01072013_30062014">Konklusion&lt;br xmlns="http://www.w3.org/1999/xhtml"/&gt;Det er vores opfattelse, at årsregnskabet giver et retvisende billede af selskabets aktiver, passiver og finansielle stilling pr. 30. juni 2014 samt af resultatet af selskabets aktiviteter for perioden 1. juli 2013 - 30. juni 2014 i overensstemmelse med årsregnskabsloven.</arr:OpinionOnAuditedFinancialStatements>
  <arr:AuditorsReportsAccordingToOtherLegislationAndRegulation contextRef="Per01072013_30062014">Erklæring i henhold til anden lovgivning og øvrig regulering</arr:AuditorsReportsAccordingToOtherLegislationAndRegulation>
  <arr:StatementOnManagementsReviewAuditorsReportOnAuditedFinancialStatements contextRef="Per01072013_30062014">Udtalelse om ledelsesberetningen&lt;br xmlns="http://www.w3.org/1999/xhtml"/&gt;Vi har i henhold til årsregnskabsloven gennemlæst ledelsesberetningen. Vi har ikke foretaget yderligere handlinger i tillæg til den udførte revision af årsregnskabet. Det er på denne baggrund vores opfattelse, at oplysningerne i ledelsesberetningen er i overensstemmelse med årsregnskabet.</arr:StatementOnManagementsReviewAuditorsReportOnAuditedFinancialStatements>
  <mrv:DescriptionOfPrimaryActivitiesOfEntity contextRef="Per01072013_30062014">Selskabets hovedaktivitet&lt;br xmlns="http://www.w3.org/1999/xhtml"/&gt;Selskabets hovedaktiviteter har i lighed med tidligere år bestået af at drive entreprenørvirksomhed.</mrv:DescriptionOfPrimaryActivitiesOfEntity>
  <mrv:DescriptionOfAnyUnusualMattersAffectingRecognitionOrMeasurement contextRef="Per01072013_30062014">Usædvanlige forhold&lt;br xmlns="http://www.w3.org/1999/xhtml"/&gt;Selskabet har fortsat sine normale driftsaktiviteter. Der har ikke været enkeltstående begivenheder i regnskabsåret, som er af så væsentlig karakter, at det kræver omtale i ledelsesberetningen.</mrv:DescriptionOfAnyUnusualMattersAffectingRecognitionOrMeasurement>
  <mrv:DescriptionOfAnyUncertaintyConnectedWithRecognitionOrMeasurement contextRef="Per01072013_30062014">Usikkerhed ved indregning og måling&lt;br xmlns="http://www.w3.org/1999/xhtml"/&gt;Der har ikke været usikkerheder vedrørende indregning eller måling i årsrapporten.</mrv:DescriptionOfAnyUncertaintyConnectedWithRecognitionOrMeasurement>
  <mrv:DescriptionOfDevelopmentInActivitiesAndFinancialAffairs contextRef="Per01072013_30062014">Udviklingen i selskabets aktiviteter og økonomiske forhold&lt;br xmlns="http://www.w3.org/1999/xhtml"/&gt;Ledelsen finder årets resultat tilfredsstillende.</mrv:DescriptionOfDevelopmentInActivitiesAndFinancialAffairs>
  <mrv:DescriptionOfSignificantEventsOccurringAfterEndOfReportingPeriod contextRef="Per01072013_30062014">Betydningsfulde hændelser indtruffet efter statusdag&lt;br xmlns="http://www.w3.org/1999/xhtml"/&gt;Der er efter regnskabsårets afslutning ikke indtruffet begivenheder, som væsentligt vil kunne påvirke selskabets finansielle stilling.</mrv:DescriptionOfSignificantEventsOccurringAfterEndOfReportingPeriod>
  <fsa:InformationOnReportingClassOfEntity contextRef="Per01072013_30062014">GENERELTÅrsregnskabet for Jens Jacobsen Byg A/S for 2013/14 er udarbejdet i overensstemmelse med årsregnskabslovens bestemmelser for selskaber i regnskabsklasse B.&lt;br xmlns="http://www.w3.org/1999/xhtml"/&gt;Årsregnskabet er aflagt efter samme regnskabspraksis som sidste år og aflægges i danske kroner.</fsa:InformationOnReportingClassOfEntity>
  <fsa:DescriptionOfGeneralMattersRelatedToRecognitionMeasurementAndChangesInAccountingPolicies contextRef="Per01072013_30062014">Generelt om indregning og måling&lt;br xmlns="http://www.w3.org/1999/xhtml"/&gt;Regnskabet er udarbejdet med udgangspunkt i det historiske kostprisprincip.&lt;br xmlns="http://www.w3.org/1999/xhtml"/&gt;Indtægter indregnes i resultatopgørelsen i takt med at de indtjenes. Herudover indregnes værdireguleringer af finansielle aktiver og forpligtelser, der måles til dagsværdi eller amortiseret kostpris. Endvidere indregnes i resultatopgørelsen alle omkostninger, der er afholdt for at opnå årets indtjening, herunder afskrivninger, nedskrivninger og hensatte forpligtelser samt tilbageførsler som følge af ændrede regnskabsmæssige skøn af beløb, der tidligere har været indregnet i resultatopgørelsen.&lt;br xmlns="http://www.w3.org/1999/xhtml"/&gt;Aktiver indregnes i balancen, når det er sandsynligt at fremtidige økonomiske fordele vil tilflyde selskabet, og aktivets værdi kan måles pålideligt.&lt;br xmlns="http://www.w3.org/1999/xhtml"/&gt;Forpligtelser indregnes i balancen, når det er sandsynligt, at fremtidige økonomiske fordele vil fragå selskabet, og forpligtelsens værdi kan måles pålideligt.&lt;br xmlns="http://www.w3.org/1999/xhtml"/&gt;Ved første indregning måles aktiver og forpligtelser til kostpris. Efterfølgende måles aktiver og forpligtelser som beskrevet for hver enkelt.&lt;br xmlns="http://www.w3.org/1999/xhtml"/&gt;Ved indregning og måling tages hensyn til forudsigelige tab og risici, der fremkommer, inden årsregnskabet aflægges, og som be- eller afkræfter forhold, der eksisterer på balancedagen.</fsa:DescriptionOfGeneralMattersRelatedToRecognitionMeasurementAndChangesInAccountingPolicies>
  <fsa:InformationOnLeasingContracts contextRef="Per01072013_30062014">Leasing&lt;br xmlns="http://www.w3.org/1999/xhtml"/&gt;Leasingkontrakter, hvor selskabet har alle væsentlige risici og fordele forbundet med ejendomsretten (finansiel leasing), indregnes i balancen til det laveste af dagsværdien af aktivet og nutidsværdien af leasingydelserne, beregnet ved anvendelse af leasingaftalens interne rentefod eller en tilnærmet værdi heraf som diskonteringsfaktor. Finansielt leasede aktiver af- og nedskrives efter samme praksis som fastlagt for selskabets øvrige anlægsaktiver.&lt;br xmlns="http://www.w3.org/1999/xhtml"/&gt;Den kapitaliserede restleasingforpligtelse indregnes i balancen som en gældsforpligtelse, og leasingydelsens rentedel omkostningsføres løbende i resultatopgørelsen.</fsa:InformationOnLeasingContracts>
  <fsa:DescriptionOfMethodsOfRecognitionAndMeasurementBasisOfIncomeStatementItems contextRef="Per01072013_30062014">RESULTATOPGØRELSEN&lt;br xmlns="http://www.w3.org/1999/xhtml"/&gt;GenereltMed henvisning til årsregnskabslovens § 32 er visse indtægter og omkostninger sammendraget i regnskabsposten bruttofortjeneste.Bruttofortjeneste Bruttofortjenesten består af sammentrækning af regnskabsposterne ”nettoomsætning, ændring i lagre af færdigvarer, varer under fremstilling og handelsvarer, andre driftsindtægter, omkostninger til råvarer og hjælpematerialer samt andre eksterne omkostninger”.</fsa:DescriptionOfMethodsOfRecognitionAndMeasurementBasisOfIncomeStatementItems>
  <fsa:DescriptionOfMethodsOfRecognitionAndMeasurementBasisOfRevenue contextRef="Per01072013_30062014">Nettoomsætning&lt;br xmlns="http://www.w3.org/1999/xhtml"/&gt;Nettoomsætningen ved salg af handelsvarer og færdigvarer indregnes i resultatopgørelsen, såfremt levering og risikoovergang til køber har fundet sted inden årets udgang. Nettoomsætningen indregnes ekskl. moms og med fradrag af rabatter i forbindelse med salget.&lt;br xmlns="http://www.w3.org/1999/xhtml"/&gt;Igangværende arbejder for fremmed regning vedrørende entreprisekontrakter indregnes i takt med, at produktionen udføres, hvorved nettoomsætningen svarer til salgsværdien af årets udførte arbejde.</fsa:DescriptionOfMethodsOfRecognitionAndMeasurementBasisOfRevenue>
  <fsa:DescriptionOfMethodsOfRecognitionAndMeasurementBasisOfCostOfSales contextRef="Per01072013_30062014">Omkostninger til råvarer og hjælpematerialerOmkostninger til råvarer og hjælpematerialer omfatter varekøb med fradrag af rabatter samt årets forskydning i varebeholdningerne.</fsa:DescriptionOfMethodsOfRecognitionAndMeasurementBasisOfCostOfSales>
  <fsa:DescriptionOfMethodsOfRecognitionAndMeasurementBasisOfExternalExpenses contextRef="Per01072013_30062014">Andre eksterne omkostningerAndre eksterne omkostninger omfatter omkostninger til salg, reklame, administration, lokaler, tab på debitorer, operationelle leasingomkostninger mv.</fsa:DescriptionOfMethodsOfRecognitionAndMeasurementBasisOfExternalExpenses>
  <fsa:DescriptionOfMethodsOfRecognitionAndMeasurementBasisOfEmployeeBenefitExpense contextRef="Per01072013_30062014">Personaleomkostninger&lt;br xmlns="http://www.w3.org/1999/xhtml"/&gt;Personaleomkostninger omfatter lønninger og øvrige lønrelaterede omkostninger, herunder sygedagpenge til virksomhedens ansatte med fradrag af lønrefusioner fra det offentlige.</fsa:DescriptionOfMethodsOfRecognitionAndMeasurementBasisOfEmployeeBenefitExpense>
  <fsa:DescriptionOfMethodsOfRecognitionAndMeasurementBasisOfFinanceIncomeAndExpenses contextRef="Per01072013_30062014">Finansielle indtægter og omkostningerFinansielle indtægter og omkostninger indregnes i resultatopgørelsen med de beløb, der vedrører regnskabsåret. Finansielle poster omfatter renteindtægter og -omkostninger, finansielle omkostninger ved finansiel leasing, realiserede og urealiserede kursgevinster og -tab vedrørende værdipapirer, amortisering af realkreditlån samt tillæg og godtgørelser under acontoskatteordningen mv.</fsa:DescriptionOfMethodsOfRecognitionAndMeasurementBasisOfFinanceIncomeAndExpenses>
  <fsa:DescriptionOfMethodsOfRecognitionAndMeasurementBasisOfTaxExpenses contextRef="Per01072013_30062014">Skat af årets resultatÅrets skat, som består af årets aktuelle skat og forskydning i udskudt skat, indregnes i resultatopgørelsen med den del, der kan henføres til årets resultat, og direkte på egenkapitalen med den del, der kan henføres til posteringer direkte på egenkapitalen.&lt;br xmlns="http://www.w3.org/1999/xhtml"/&gt;Moderselskabet og de danske koncernvirksomheder er sambeskattede. Den danske selskabsskat fordeles mellem de sambeskattede danske selskaber i forhold til disses skattepligtige indkomster. Moderselskabet fungerer som administrationsselskab for sambeskatningskredsen, således at moderselskabet forestår afregning af skatter mv. til de danske skattemyndigheder.</fsa:DescriptionOfMethodsOfRecognitionAndMeasurementBasisOfTaxExpenses>
  <fsa:DescriptionOfMethodsOfRecognitionAndMeasurementBasisOfAssetsAndLiabilities contextRef="Per01072013_30062014">BALANCEN</fsa:DescriptionOfMethodsOfRecognitionAndMeasurementBasisOfAssetsAndLiabilities>
  <fsa:DescriptionOfMethodsOfRecognitionAndMeasurementBasisOfIntangibleAssets contextRef="Per01072013_30062014">Immaterielle anlægsaktiver&lt;br xmlns="http://www.w3.org/1999/xhtml"/&gt;Goodwill&lt;br xmlns="http://www.w3.org/1999/xhtml"/&gt;Erhvervet goodwill måles til kostpris med fradrag af akkumulerede afskrivninger. Goodwill afskrives lineært over den vurderede økonomiske brugstid, der er vurderet til 5 år.</fsa:DescriptionOfMethodsOfRecognitionAndMeasurementBasisOfIntangibleAssets>
  <fsa:DescriptionOfMethodsOfRecognitionAndMeasurementBasisOfPropertyPlantAndEquipment contextRef="Per01072013_30062014">Materielle anlægsaktiver&lt;br xmlns="http://www.w3.org/1999/xhtml"/&gt;Materielle anlægsaktiver måles til kostpris med fradrag af akkumulerede af- og nedskrivninger.&lt;br xmlns="http://www.w3.org/1999/xhtml"/&gt;Afskrivningsgrundlaget er kostpris med fradrag af forventet restværdi efter afsluttet brugstid. Der afskrives ikke på grunde.Kostprisen omfatter anskaffelsesprisen samt omkostninger direkte tilknyttet anskaffelsen indtil det tidspunkt, hvor aktivet er klar til at blive taget i brug. For egenfremstillede aktiver omfatter kostprisen omkostninger til materialer, komponenter, underleverandører, direkte lønforbrug samt indirekte produktionsomkostninger. Der foretages lineære afskrivninger baseret på følgende vurdering af aktivernes forventede brugstider:&lt;br xmlns="http://www.w3.org/1999/xhtml"/&gt;BrugstidBygninger50 årTekniske anlæg og maskiner3-5 årAndre anlæg, driftsmateriel og inventar3-5 år&lt;br xmlns="http://www.w3.org/1999/xhtml"/&gt;&lt;br xmlns="http://www.w3.org/1999/xhtml"/&gt;Fortjeneste eller tab ved afhændelse af materielle anlægsaktiver opgøres som forskellen mellem salgspris med fradrag af salgsomkostninger og den regnskabsmæssige værdi på salgstidspunktet. Fortjeneste eller tab indregnes i resultatopgørelsen under andre driftsindtægter/andre driftsomkostninger.</fsa:DescriptionOfMethodsOfRecognitionAndMeasurementBasisOfPropertyPlantAndEquipment>
  <fsa:DescriptionOfMethodsOfRecognitionAndMeasurementBasisOfInventories contextRef="Per01072013_30062014">Varebeholdninger&lt;br xmlns="http://www.w3.org/1999/xhtml"/&gt;Varebeholdninger måles til kostpris på grundlag af vejede gennemsnitspriser. I tilfælde, hvor kostprisen er højere end nettorealisationsværdien, nedskrives til denne lavere værdi.</fsa:DescriptionOfMethodsOfRecognitionAndMeasurementBasisOfInventories>
  <fsa:DescriptionOfMethodsOfRecognitionAndMeasurementBasisOfReceivables contextRef="Per01072013_30062014">TilgodehavenderTilgodehavender måles til amortiseret kostpris, hvilket sædvanligvis svarer til nominel værdi. Værdien reduceres med nedskrivning til imødegåelse af forventede tab.</fsa:DescriptionOfMethodsOfRecognitionAndMeasurementBasisOfReceivables>
  <fsa:DescriptionOfMethodsOfRecognitionAndMeasurementBasisOfContractWorkInProgress contextRef="Per01072013_30062014">Igangværende arbejder for fremmed regningIgangværende arbejder for fremmed regning måles til salgsværdien af det udførte arbejde. Salgsværdien måles på baggrund af færdiggørelsesgraden på balancedagen og de samlede forventede indtægter på det enkelte igangværende arbejde. Når salgsværdien ikke kan opgøres pålideligt, måles salgsværdien til de medgåede omkostninger eller nettorealisationsværdien, såfremt denne er lavere. Omkostninger i forbindelse med salgsarbejde og opnåelse af kontrakter indregnes i resultatopgørelsen i takt med, at de afholdes.</fsa:DescriptionOfMethodsOfRecognitionAndMeasurementBasisOfContractWorkInProgress>
  <fsa:DescriptionOfMethodsOfRecognitionAndMeasurementBasisOfDeferredIncomeAssets contextRef="Per01072013_30062014">PeriodeafgrænsningsposterPeriodeafgrænsningsposter indregnet under aktiver omfatter afholdte omkostninger vedrørende efterfølgende regnskabsår.</fsa:DescriptionOfMethodsOfRecognitionAndMeasurementBasisOfDeferredIncomeAssets>
  <fsa:DescriptionOfMethodsOfInvestmentsAsCurrentAssets contextRef="Per01072013_30062014">Værdipapirer og kapitalandele&lt;br xmlns="http://www.w3.org/1999/xhtml"/&gt;Værdipapirer og kapitalandele, indregnet under omsætningsaktiver, omfatter værdipapirer optaget til handel på et reguleret marked, der måles til dagsværdien på balancedagen. Dagsværdien opgøres på grundlag af den senest noterede salgskurs.</fsa:DescriptionOfMethodsOfInvestmentsAsCurrentAssets>
  <fsa:DescriptionOfMethodsOfRecognitionAndMeasurementBasisOfTaxPayablesAndDeferredTax contextRef="Per01072013_30062014">Selskabsskat og udskudt skatAktuelle skatteforpligtelser og tilgodehavende aktuel skat indregnes i balancen som beregnet skat af årets skattepligtige indkomst reguleret for skat af tidligere års skattepligtige indkomster samt for betalte acontoskatter.Udskudt skat måles efter den balanceorienterede gældsmetode af midlertidige forskelle mellem regnskabsmæssig og skattemæssig værdi af aktiver og forpligtelser. I de tilfælde, f.eks. vedrørende aktier, hvor opgørelse af skatteværdien kan foretages efter alternative beskatningsregler, måles udskudt skat på grundlag af den planlagte anvendelse af aktivet henholdsvis afvikling af forpligtelsen.Udskudte skatteaktiver, herunder skatteværdien af fremførselsberettiget skattemæssigt underskud, måles til den værdi, hvortil aktivet forventes at kunne realiseres, enten ved udligning i skat af fremtidig indtjening eller ved modregning i udskudte skatteforpligtelser inden for samme juridiske skatteenhed. Eventuelle udskudte nettoskatteaktiver måles til nettorealisationsværdi.&lt;br xmlns="http://www.w3.org/1999/xhtml"/&gt;Selskabsskatteprocenten nedsættes gradvist fra 25% til 22% i indkomstårene 2014 – 2016. Udskudt skat måles på grundlag af de skatteregler og skattesatser, der med balancedagens lovgivning vil være gældende, når den udskudte skat forventes udløst som aktuel skat. For indeværende år er anvendt en skattesats på 23%.</fsa:DescriptionOfMethodsOfRecognitionAndMeasurementBasisOfTaxPayablesAndDeferredTax>
  <fsa:DescriptionOfMethodsOfRecognitionAndMeasurementBasisOfLiabilitiesOtherThanProvisions contextRef="Per01072013_30062014">Gældsforpligtelser&lt;br xmlns="http://www.w3.org/1999/xhtml"/&gt;Finansielle gældsforpligtelser indregnes ved lånoptagelse til det modtagne provenu med fradrag af afholdte transaktionsomkostninger. I efterfølgende perioder måles de finansielle forpligtelser til amortiseret kostpris svarende til den kapitaliserede værdi ved anvendelse af den effektive rente, således at forskellen mellem provenuet og den nominelle værdi indregnes i resultatopgørelsen over låneperioden.&lt;br xmlns="http://www.w3.org/1999/xhtml"/&gt;Prioritetsgæld er således målt til amortiseret kostpris, der for kontantlån svarer til lånets restgæld. For obligationslån svarer amortiseret kostpris til en restgæld beregnet som lånets underliggende kontantværdi på lånoptagelsestidspunktet reguleret med en over afdragstiden foretaget afskrivning af lånets kursregulering på optagelsestidspunktet.&lt;br xmlns="http://www.w3.org/1999/xhtml"/&gt;Andre gældsforpligtelser, som omfatter gæld til leverandører, tilknyttede og associerede virksomheder samt anden gæld, måles til amortiseret kostpris, hvilket sædvanligvis svarer til nominel værdi.</fsa:DescriptionOfMethodsOfRecognitionAndMeasurementBasisOfLiabilitiesOtherThanProvisions>
  <fsa:GrossProfitLoss contextRef="Per01072013_30062014" decimals="0" unitRef="DKK">4112718</fsa:GrossProfitLoss>
  <fsa:EmployeeBenefitsExpense contextRef="Per01072013_30062014" decimals="0" unitRef="DKK">3537469</fsa:EmployeeBenefitsExpense>
  <fsa:DepreciationAmortisationExpenseAndImpairmentLossesOfPropertyPlantAndEquipmentAndIntangibleAssetsRecognisedInProfitOrLoss contextRef="Per01072013_30062014" decimals="0" unitRef="DKK">323313</fsa:DepreciationAmortisationExpenseAndImpairmentLossesOfPropertyPlantAndEquipmentAndIntangibleAssetsRecognisedInProfitOrLoss>
  <fsa:OtherOperatingExpenses contextRef="Per01072013_30062014" decimals="0" unitRef="DKK">17583</fsa:OtherOperatingExpenses>
  <fsa:ProfitLossFromOrdinaryOperatingActivities contextRef="Per01072013_30062014" decimals="0" unitRef="DKK">234353</fsa:ProfitLossFromOrdinaryOperatingActivities>
  <fsa:OtherFinanceIncome contextRef="Per01072013_30062014" decimals="0" unitRef="DKK">6490</fsa:OtherFinanceIncome>
  <fsa:OtherFinanceIncomeFromGroupEnterprises contextRef="Per01072013_30062014" decimals="0" unitRef="DKK">4086</fsa:OtherFinanceIncomeFromGroupEnterprises>
  <fsa:RestOfOtherFinanceExpenses contextRef="Per01072013_30062014" decimals="0" unitRef="DKK">86139</fsa:RestOfOtherFinanceExpenses>
  <fsa:TaxExpense contextRef="Per01072013_30062014" decimals="0" unitRef="DKK">75165</fsa:TaxExpense>
  <fsa:ProfitLoss contextRef="Per01072013_30062014" decimals="0" unitRef="DKK">83625</fsa:ProfitLoss>
  <fsa:DisclosureOfEmployeeBenefitsExpense contextRef="Per01072013_30062014">1 Personaleomkostninger &lt;br xmlns="http://www.w3.org/1999/xhtml"/&gt; Lønninger  2.943.368 2.604.563&lt;br xmlns="http://www.w3.org/1999/xhtml"/&gt; Pensioner  428.383 366.780&lt;br xmlns="http://www.w3.org/1999/xhtml"/&gt; Andre omkostninger til social sikring  165.718 150.287&lt;br xmlns="http://www.w3.org/1999/xhtml"/&gt;    &lt;br xmlns="http://www.w3.org/1999/xhtml"/&gt; 3.537.469 3.121.630&lt;br xmlns="http://www.w3.org/1999/xhtml"/&gt;    &lt;br xmlns="http://www.w3.org/1999/xhtml"/&gt;  &lt;br xmlns="http://www.w3.org/1999/xhtml"/&gt;    &lt;br xmlns="http://www.w3.org/1999/xhtml"/&gt;</fsa:DisclosureOfEmployeeBenefitsExpense>
  <fsa:DisclosureOfOtherFinanceIncome contextRef="Per01072013_30062014">2 Andre finansielle indtægter fra tilknyttede virksomheder &lt;br xmlns="http://www.w3.org/1999/xhtml"/&gt; Rente Ranga Invest ApS  4.086 3.712&lt;br xmlns="http://www.w3.org/1999/xhtml"/&gt;    &lt;br xmlns="http://www.w3.org/1999/xhtml"/&gt; 4.086 3.712&lt;br xmlns="http://www.w3.org/1999/xhtml"/&gt;    &lt;br xmlns="http://www.w3.org/1999/xhtml"/&gt;    &lt;br xmlns="http://www.w3.org/1999/xhtml"/&gt;</fsa:DisclosureOfOtherFinanceIncome>
  <fsa:DisclosureOfTaxExpenses contextRef="Per01072013_30062014">3 Skat af årets resultat &lt;br xmlns="http://www.w3.org/1999/xhtml"/&gt; Regulering af udskudt skat  75.165 103.412&lt;br xmlns="http://www.w3.org/1999/xhtml"/&gt;    &lt;br xmlns="http://www.w3.org/1999/xhtml"/&gt; 75.165 103.412&lt;br xmlns="http://www.w3.org/1999/xhtml"/&gt;    &lt;br xmlns="http://www.w3.org/1999/xhtml"/&gt;    &lt;br xmlns="http://www.w3.org/1999/xhtml"/&gt;</fsa:DisclosureOfTaxExpenses>
  <fsa:DisclosureOfIntangibleAssets contextRef="Per01072013_30062014">4 Immaterielle anlægsaktiver &lt;br xmlns="http://www.w3.org/1999/xhtml"/&gt; Anskaffelsessum, primo  53.027&lt;br xmlns="http://www.w3.org/1999/xhtml"/&gt; Tilgang i årets løb  0&lt;br xmlns="http://www.w3.org/1999/xhtml"/&gt; Afgang i årets løb  0&lt;br xmlns="http://www.w3.org/1999/xhtml"/&gt;  &lt;br xmlns="http://www.w3.org/1999/xhtml"/&gt; Anskaffelsessum 30. juni 2014  53.027&lt;br xmlns="http://www.w3.org/1999/xhtml"/&gt;  &lt;br xmlns="http://www.w3.org/1999/xhtml"/&gt;  &lt;br xmlns="http://www.w3.org/1999/xhtml"/&gt; Af-/nedskrivninger, primo  -45.956&lt;br xmlns="http://www.w3.org/1999/xhtml"/&gt; Af-/nedskrivninger på afhændede aktiver  0&lt;br xmlns="http://www.w3.org/1999/xhtml"/&gt; Årets af-/nedskrivninger  -7.071&lt;br xmlns="http://www.w3.org/1999/xhtml"/&gt;  &lt;br xmlns="http://www.w3.org/1999/xhtml"/&gt; Af-/nedskrivninger 30. juni 2014  -53.027&lt;br xmlns="http://www.w3.org/1999/xhtml"/&gt;  &lt;br xmlns="http://www.w3.org/1999/xhtml"/&gt; Regnskabsmæssig værdi 30. juni 2014  0&lt;br xmlns="http://www.w3.org/1999/xhtml"/&gt;  &lt;br xmlns="http://www.w3.org/1999/xhtml"/&gt;  &lt;br xmlns="http://www.w3.org/1999/xhtml"/&gt;    &lt;br xmlns="http://www.w3.org/1999/xhtml"/&gt;</fsa:DisclosureOfIntangibleAssets>
  <fsa:DisclosureOfPropertyPlantAndEquipment contextRef="Per01072013_30062014">5 Materielle anlægsaktiver &lt;br xmlns="http://www.w3.org/1999/xhtml"/&gt; Anskaffelsessum, primo  1.605.087 1.793.513&lt;br xmlns="http://www.w3.org/1999/xhtml"/&gt; Tilgang i årets løb  0 328.396&lt;br xmlns="http://www.w3.org/1999/xhtml"/&gt; Afgang i årets løb  0 0&lt;br xmlns="http://www.w3.org/1999/xhtml"/&gt;    &lt;br xmlns="http://www.w3.org/1999/xhtml"/&gt; Anskaffelsessum 30. juni 2014  1.605.087 2.121.909&lt;br xmlns="http://www.w3.org/1999/xhtml"/&gt;    &lt;br xmlns="http://www.w3.org/1999/xhtml"/&gt;  &lt;br xmlns="http://www.w3.org/1999/xhtml"/&gt; Af-/nedskrivninger, primo  -310.087 -1.102.654&lt;br xmlns="http://www.w3.org/1999/xhtml"/&gt; Af-/nedskrivninger på afhændede aktiver  0 0&lt;br xmlns="http://www.w3.org/1999/xhtml"/&gt; Årets af-/nedskrivninger  -9.900 -306.341&lt;br xmlns="http://www.w3.org/1999/xhtml"/&gt;    &lt;br xmlns="http://www.w3.org/1999/xhtml"/&gt; Af-/nedskrivninger 30. juni 2014  -319.987 -1.408.995&lt;br xmlns="http://www.w3.org/1999/xhtml"/&gt;    &lt;br xmlns="http://www.w3.org/1999/xhtml"/&gt; Regnskabsmæssig værdi 30. juni 2014  1.285.100 712.914&lt;br xmlns="http://www.w3.org/1999/xhtml"/&gt;    &lt;br xmlns="http://www.w3.org/1999/xhtml"/&gt;  &lt;br xmlns="http://www.w3.org/1999/xhtml"/&gt; Heraf finansielle leasingaktiver  0 573.000&lt;br xmlns="http://www.w3.org/1999/xhtml"/&gt;    &lt;br xmlns="http://www.w3.org/1999/xhtml"/&gt;  &lt;br xmlns="http://www.w3.org/1999/xhtml"/&gt;    &lt;br xmlns="http://www.w3.org/1999/xhtml"/&gt;</fsa:DisclosureOfPropertyPlantAndEquipment>
  <fsa:DisclosureOfEquity contextRef="Per01072013_30062014">6 Egenkapital &lt;br xmlns="http://www.w3.org/1999/xhtml"/&gt;  &lt;br xmlns="http://www.w3.org/1999/xhtml"/&gt;  &lt;br xmlns="http://www.w3.org/1999/xhtml"/&gt; Virksomhedskapital  500.000 0 500.000&lt;br xmlns="http://www.w3.org/1999/xhtml"/&gt; Overført resultat  988.293 83.625 1.071.918&lt;br xmlns="http://www.w3.org/1999/xhtml"/&gt;      &lt;br xmlns="http://www.w3.org/1999/xhtml"/&gt; 1.488.293 83.625 1.571.918&lt;br xmlns="http://www.w3.org/1999/xhtml"/&gt;      &lt;br xmlns="http://www.w3.org/1999/xhtml"/&gt;  &lt;br xmlns="http://www.w3.org/1999/xhtml"/&gt;   &lt;br xmlns="http://www.w3.org/1999/xhtml"/&gt;   &lt;br xmlns="http://www.w3.org/1999/xhtml"/&gt;     &lt;br xmlns="http://www.w3.org/1999/xhtml"/&gt;</fsa:DisclosureOfEquity>
  <fsa:DisclosureOfLongtermLiabilities contextRef="Per01072013_30062014">7 Langfristede gældsforpligtelser &lt;br xmlns="http://www.w3.org/1999/xhtml"/&gt;  &lt;br xmlns="http://www.w3.org/1999/xhtml"/&gt; Prioritetsgæld  840.000 0 809.249&lt;br xmlns="http://www.w3.org/1999/xhtml"/&gt; Leasingforpligtelser  531.516 214.200 0&lt;br xmlns="http://www.w3.org/1999/xhtml"/&gt;      &lt;br xmlns="http://www.w3.org/1999/xhtml"/&gt; 1.371.516 214.200 809.249&lt;br xmlns="http://www.w3.org/1999/xhtml"/&gt;      &lt;br xmlns="http://www.w3.org/1999/xhtml"/&gt;  &lt;br xmlns="http://www.w3.org/1999/xhtml"/&gt;     &lt;br xmlns="http://www.w3.org/1999/xhtml"/&gt;</fsa:DisclosureOfLongtermLiabilities>
  <fsa:DisclosureOfContingentLiabilities contextRef="Per01072013_30062014">8 Eventualposter mv. &lt;br xmlns="http://www.w3.org/1999/xhtml"/&gt;  Garantiforpligtelse andrager kr. 118.300, beløbet vedrører arbejdsgarantier.&lt;br xmlns="http://www.w3.org/1999/xhtml"/&gt;&lt;br xmlns="http://www.w3.org/1999/xhtml"/&gt;Leasingforpligtelse andrager kr. 174.594.&lt;br xmlns="http://www.w3.org/1999/xhtml"/&gt; &lt;br xmlns="http://www.w3.org/1999/xhtml"/&gt;   Selskabet har indgået huslejekontrakt som tidligst kan opsiges med 3 måneders varsel. Forpligtelsen udgør kr. 45.000.&lt;br xmlns="http://www.w3.org/1999/xhtml"/&gt;&lt;br xmlns="http://www.w3.org/1999/xhtml"/&gt;                   &lt;br xmlns="http://www.w3.org/1999/xhtml"/&gt;</fsa:DisclosureOfContingentLiabilities>
  <fsa:DisclosureOfMortgagesAndCollaterals contextRef="Per01072013_30062014">9 Pantsætninger og sikkerhedsstillelser &lt;br xmlns="http://www.w3.org/1999/xhtml"/&gt; Der er pant i ejendommen på kr. 840.000, pantet ligger til sikkerhed for prioritetsgæld. &lt;br xmlns="http://www.w3.org/1999/xhtml"/&gt;&lt;br xmlns="http://www.w3.org/1999/xhtml"/&gt;Der er ejerpantebrev kr. 300.000 med pant i ejendommen, som ligger til sikkerhed for vareleverancer.&lt;br xmlns="http://www.w3.org/1999/xhtml"/&gt;&lt;br xmlns="http://www.w3.org/1999/xhtml"/&gt;Selskabet har afgivet selvskyldnerkaution for alt mellemværende mellem pengeinstitut og LD Magleby Holding ApS og JD Entreprise ApS.&lt;br xmlns="http://www.w3.org/1999/xhtml"/&gt;&lt;br xmlns="http://www.w3.org/1999/xhtml"/&gt;Leasede aktiver ligger til sikkerhed for leasinggæld.&lt;br xmlns="http://www.w3.org/1999/xhtml"/&gt;&lt;br xmlns="http://www.w3.org/1999/xhtml"/&gt;                     &lt;br xmlns="http://www.w3.org/1999/xhtml"/&gt;</fsa:DisclosureOfMortgagesAndCollaterals>
  <fsa:DisclosureOfOwnership contextRef="Per01072013_30062014">10 Ejerforhold &lt;br xmlns="http://www.w3.org/1999/xhtml"/&gt; Ranga Invest ApS&lt;br xmlns="http://www.w3.org/1999/xhtml"/&gt;Borgergade 12&lt;br xmlns="http://www.w3.org/1999/xhtml"/&gt;4672 Klippinge           &lt;br xmlns="http://www.w3.org/1999/xhtml"/&gt;</fsa:DisclosureOfOwnership>
  <fsa:GrossProfitLoss contextRef="Per01072012_30062013" decimals="0" unitRef="DKK">3904376</fsa:GrossProfitLoss>
  <fsa:EmployeeBenefitsExpense contextRef="Per01072012_30062013" decimals="0" unitRef="DKK">3121630</fsa:EmployeeBenefitsExpense>
  <fsa:DepreciationAmortisationExpenseAndImpairmentLossesOfPropertyPlantAndEquipmentAndIntangibleAssetsRecognisedInProfitOrLoss contextRef="Per01072012_30062013" decimals="0" unitRef="DKK">252529</fsa:DepreciationAmortisationExpenseAndImpairmentLossesOfPropertyPlantAndEquipmentAndIntangibleAssetsRecognisedInProfitOrLoss>
  <fsa:OtherOperatingExpenses contextRef="Per01072012_30062013" decimals="0" unitRef="DKK">40244</fsa:OtherOperatingExpenses>
  <fsa:ProfitLossFromOrdinaryOperatingActivities contextRef="Per01072012_30062013" decimals="0" unitRef="DKK">489973</fsa:ProfitLossFromOrdinaryOperatingActivities>
  <fsa:OtherFinanceIncome contextRef="Per01072012_30062013" decimals="0" unitRef="DKK">2270</fsa:OtherFinanceIncome>
  <fsa:OtherFinanceIncomeFromGroupEnterprises contextRef="Per01072012_30062013" decimals="0" unitRef="DKK">3712</fsa:OtherFinanceIncomeFromGroupEnterprises>
  <fsa:RestOfOtherFinanceExpenses contextRef="Per01072012_30062013" decimals="0" unitRef="DKK">96200</fsa:RestOfOtherFinanceExpenses>
  <fsa:TaxExpense contextRef="Per01072012_30062013" decimals="0" unitRef="DKK">103412</fsa:TaxExpense>
  <fsa:ProfitLoss contextRef="Per01072012_30062013" decimals="0" unitRef="DKK">296343</fsa:ProfitLoss>
  <fsa:Goodwill contextRef="Per01072013_30062014-Instant" decimals="0" unitRef="DKK">0</fsa:Goodwill>
  <fsa:IntangibleAssets contextRef="Per01072013_30062014-Instant" decimals="0" unitRef="DKK">0</fsa:IntangibleAssets>
  <fsa:LandAndBuildings contextRef="Per01072013_30062014-Instant" decimals="0" unitRef="DKK">1285100</fsa:LandAndBuildings>
  <fsa:FixturesFittingsToolsAndEquipment contextRef="Per01072013_30062014-Instant" decimals="0" unitRef="DKK">712914</fsa:FixturesFittingsToolsAndEquipment>
  <fsa:PropertyPlantAndEquipment contextRef="Per01072013_30062014-Instant" decimals="0" unitRef="DKK">1998014</fsa:PropertyPlantAndEquipment>
  <fsa:NoncurrentAssets contextRef="Per01072013_30062014-Instant" decimals="0" unitRef="DKK">1998014</fsa:NoncurrentAssets>
  <fsa:RawMaterialsAndConsumables contextRef="Per01072013_30062014-Instant" decimals="0" unitRef="DKK">535323</fsa:RawMaterialsAndConsumables>
  <fsa:Inventories contextRef="Per01072013_30062014-Instant" decimals="0" unitRef="DKK">535323</fsa:Inventories>
  <fsa:ShorttermTradeReceivables contextRef="Per01072013_30062014-Instant" decimals="0" unitRef="DKK">547204</fsa:ShorttermTradeReceivables>
  <fsa:ContractWorkInProgress contextRef="Per01072013_30062014-Instant" decimals="0" unitRef="DKK">963966</fsa:ContractWorkInProgress>
  <fsa:ShorttermReceivablesFromGroupEnterprises contextRef="Per01072013_30062014-Instant" decimals="0" unitRef="DKK">213917</fsa:ShorttermReceivablesFromGroupEnterprises>
  <fsa:OtherShorttermReceivables contextRef="Per01072013_30062014-Instant" decimals="0" unitRef="DKK">342329</fsa:OtherShorttermReceivables>
  <fsa:CurrentDeferredTaxAssets contextRef="Per01072013_30062014-Instant" decimals="0" unitRef="DKK">269292</fsa:CurrentDeferredTaxAssets>
  <fsa:DeferredIncomeAssets contextRef="Per01072013_30062014-Instant" decimals="0" unitRef="DKK">169313</fsa:DeferredIncomeAssets>
  <fsa:ShorttermReceivables contextRef="Per01072013_30062014-Instant" decimals="0" unitRef="DKK">2506021</fsa:ShorttermReceivables>
  <fsa:OtherShorttermInvestments contextRef="Per01072013_30062014-Instant" decimals="0" unitRef="DKK">618</fsa:OtherShorttermInvestments>
  <fsa:ShorttermInvestments contextRef="Per01072013_30062014-Instant" decimals="0" unitRef="DKK">618</fsa:ShorttermInvestments>
  <fsa:CashAndCashEquivalents contextRef="Per01072013_30062014-Instant" decimals="0" unitRef="DKK">160024</fsa:CashAndCashEquivalents>
  <fsa:CurrentAssets contextRef="Per01072013_30062014-Instant" decimals="0" unitRef="DKK">3201986</fsa:CurrentAssets>
  <fsa:Assets contextRef="Per01072013_30062014-Instant" decimals="0" unitRef="DKK">5200000</fsa:Assets>
  <fsa:ContributedCapital contextRef="Per01072013_30062014-Instant" decimals="0" unitRef="DKK">500000</fsa:ContributedCapital>
  <fsa:RetainedEarnings contextRef="Per01072013_30062014-Instant" decimals="0" unitRef="DKK">1071918</fsa:RetainedEarnings>
  <fsa:Equity contextRef="Per01072013_30062014-Instant" decimals="0" unitRef="DKK">1571918</fsa:Equity>
  <fsa:LongtermMortgageDebt contextRef="Per01072013_30062014-Instant" decimals="0" unitRef="DKK">840000</fsa:LongtermMortgageDebt>
  <fsa:LongtermLeaseCommitments contextRef="Per01072013_30062014-Instant" decimals="0" unitRef="DKK">317316</fsa:LongtermLeaseCommitments>
  <fsa:LongtermLiabilitiesOtherThanProvisions contextRef="Per01072013_30062014-Instant" decimals="0" unitRef="DKK">1157316</fsa:LongtermLiabilitiesOtherThanProvisions>
  <fsa:ShorttermPartOfLongtermLiabilitiesOtherThanProvisions contextRef="Per01072013_30062014-Instant" decimals="0" unitRef="DKK">214200</fsa:ShorttermPartOfLongtermLiabilitiesOtherThanProvisions>
  <fsa:ShorttermTradePayables contextRef="Per01072013_30062014-Instant" decimals="0" unitRef="DKK">1015436</fsa:ShorttermTradePayables>
  <fsa:OtherShorttermPayables contextRef="Per01072013_30062014-Instant" decimals="0" unitRef="DKK">781696</fsa:OtherShorttermPayables>
  <fsa:ShorttermPayablesToShareholdersAndManagement contextRef="Per01072013_30062014-Instant" decimals="0" unitRef="DKK">459434</fsa:ShorttermPayablesToShareholdersAndManagement>
  <fsa:ShorttermLiabilitiesOtherThanProvisions contextRef="Per01072013_30062014-Instant" decimals="0" unitRef="DKK">2470766</fsa:ShorttermLiabilitiesOtherThanProvisions>
  <fsa:LiabilitiesOtherThanProvisions contextRef="Per01072013_30062014-Instant" decimals="0" unitRef="DKK">3628082</fsa:LiabilitiesOtherThanProvisions>
  <fsa:LiabilitiesAndEquity contextRef="Per01072013_30062014-Instant" decimals="0" unitRef="DKK">5200000</fsa:LiabilitiesAndEquity>
  <fsa:Goodwill contextRef="Per01072012_30062013-Instant" decimals="0" unitRef="DKK">7072</fsa:Goodwill>
  <fsa:IntangibleAssets contextRef="Per01072012_30062013-Instant" decimals="0" unitRef="DKK">7072</fsa:IntangibleAssets>
  <fsa:LandAndBuildings contextRef="Per01072012_30062013-Instant" decimals="0" unitRef="DKK">0</fsa:LandAndBuildings>
  <fsa:FixturesFittingsToolsAndEquipment contextRef="Per01072012_30062013-Instant" decimals="0" unitRef="DKK">690861</fsa:FixturesFittingsToolsAndEquipment>
  <fsa:PropertyPlantAndEquipment contextRef="Per01072012_30062013-Instant" decimals="0" unitRef="DKK">690861</fsa:PropertyPlantAndEquipment>
  <fsa:NoncurrentAssets contextRef="Per01072012_30062013-Instant" decimals="0" unitRef="DKK">697933</fsa:NoncurrentAssets>
  <fsa:RawMaterialsAndConsumables contextRef="Per01072012_30062013-Instant" decimals="0" unitRef="DKK">150000</fsa:RawMaterialsAndConsumables>
  <fsa:Inventories contextRef="Per01072012_30062013-Instant" decimals="0" unitRef="DKK">150000</fsa:Inventories>
  <fsa:ShorttermTradeReceivables contextRef="Per01072012_30062013-Instant" decimals="0" unitRef="DKK">562523</fsa:ShorttermTradeReceivables>
  <fsa:ContractWorkInProgress contextRef="Per01072012_30062013-Instant" decimals="0" unitRef="DKK">654391</fsa:ContractWorkInProgress>
  <fsa:ShorttermReceivablesFromGroupEnterprises contextRef="Per01072012_30062013-Instant" decimals="0" unitRef="DKK">196519</fsa:ShorttermReceivablesFromGroupEnterprises>
  <fsa:OtherShorttermReceivables contextRef="Per01072012_30062013-Instant" decimals="0" unitRef="DKK">1607207</fsa:OtherShorttermReceivables>
  <fsa:CurrentDeferredTaxAssets contextRef="Per01072012_30062013-Instant" decimals="0" unitRef="DKK">344457</fsa:CurrentDeferredTaxAssets>
  <fsa:DeferredIncomeAssets contextRef="Per01072012_30062013-Instant" decimals="0" unitRef="DKK">156654</fsa:DeferredIncomeAssets>
  <fsa:ShorttermReceivables contextRef="Per01072012_30062013-Instant" decimals="0" unitRef="DKK">3521751</fsa:ShorttermReceivables>
  <fsa:OtherShorttermInvestments contextRef="Per01072012_30062013-Instant" decimals="0" unitRef="DKK">432</fsa:OtherShorttermInvestments>
  <fsa:ShorttermInvestments contextRef="Per01072012_30062013-Instant" decimals="0" unitRef="DKK">432</fsa:ShorttermInvestments>
  <fsa:CashAndCashEquivalents contextRef="Per01072012_30062013-Instant" decimals="0" unitRef="DKK">607315</fsa:CashAndCashEquivalents>
  <fsa:CurrentAssets contextRef="Per01072012_30062013-Instant" decimals="0" unitRef="DKK">4279498</fsa:CurrentAssets>
  <fsa:Assets contextRef="Per01072012_30062013-Instant" decimals="0" unitRef="DKK">4977431</fsa:Assets>
  <fsa:ContributedCapital contextRef="Per01072012_30062013-Instant" decimals="0" unitRef="DKK">500000</fsa:ContributedCapital>
  <fsa:RetainedEarnings contextRef="Per01072012_30062013-Instant" decimals="0" unitRef="DKK">988293</fsa:RetainedEarnings>
  <fsa:Equity contextRef="Per01072012_30062013-Instant" decimals="0" unitRef="DKK">1488293</fsa:Equity>
  <fsa:LongtermMortgageDebt contextRef="Per01072012_30062013-Instant" decimals="0" unitRef="DKK">0</fsa:LongtermMortgageDebt>
  <fsa:LongtermLeaseCommitments contextRef="Per01072012_30062013-Instant" decimals="0" unitRef="DKK">375618</fsa:LongtermLeaseCommitments>
  <fsa:LongtermLiabilitiesOtherThanProvisions contextRef="Per01072012_30062013-Instant" decimals="0" unitRef="DKK">375618</fsa:LongtermLiabilitiesOtherThanProvisions>
  <fsa:ShorttermPartOfLongtermLiabilitiesOtherThanProvisions contextRef="Per01072012_30062013-Instant" decimals="0" unitRef="DKK">1077544</fsa:ShorttermPartOfLongtermLiabilitiesOtherThanProvisions>
  <fsa:ShorttermTradePayables contextRef="Per01072012_30062013-Instant" decimals="0" unitRef="DKK">664473</fsa:ShorttermTradePayables>
  <fsa:OtherShorttermPayables contextRef="Per01072012_30062013-Instant" decimals="0" unitRef="DKK">921078</fsa:OtherShorttermPayables>
  <fsa:ShorttermPayablesToShareholdersAndManagement contextRef="Per01072012_30062013-Instant" decimals="0" unitRef="DKK">450425</fsa:ShorttermPayablesToShareholdersAndManagement>
  <fsa:ShorttermLiabilitiesOtherThanProvisions contextRef="Per01072012_30062013-Instant" decimals="0" unitRef="DKK">3113520</fsa:ShorttermLiabilitiesOtherThanProvisions>
  <fsa:LiabilitiesOtherThanProvisions contextRef="Per01072012_30062013-Instant" decimals="0" unitRef="DKK">3489138</fsa:LiabilitiesOtherThanProvisions>
  <fsa:LiabilitiesAndEquity contextRef="Per01072012_30062013-Instant" decimals="0" unitRef="DKK">4977431</fsa:LiabilitiesAndEquity>
  <cmn:NameAndSurnameOfMemberOfExecutiveBoard contextRef="Per01072013_30062014_0_Identifikation_af_medlem_af_direktionen">Dennis Jacobsen</cmn:NameAndSurnameOfMemberOfExecutiveBoard>
  <cmn:NameAndSurnameOfMemberOfSupervisoryBoard contextRef="Per01072013_30062014_1_Identifikation_af_medlem_af_bestyrelsen">Lennart Jacobsen</cmn:NameAndSurnameOfMemberOfSupervisoryBoard>
  <cmn:NameAndSurnameOfMemberOfSupervisoryBoard contextRef="Per01072013_30062014_2_Identifikation_af_medlem_af_bestyrelsen">Jacob Skov JacobsenDennis Jacobsen</cmn:NameAndSurnameOfMemberOfSupervisoryBoard>
  <cmn:NameAndSurnameOfAuditor contextRef="Per01072013_30062014_3_Identifikation_af_revisor">Torben Wind</cmn:NameAndSurnameOfAuditor>
  <cmn:NameOfAuditFirm contextRef="Per01072013_30062014_3_Identifikation_af_revisor">Wind Revision, Registreret Revisionsanpartsselskab</cmn:NameOfAuditFirm>
  <cmn:DescriptionOfAuditor contextRef="Per01072013_30062014_3_Identifikation_af_revisor">Registreret revisor</cmn:DescriptionOfAuditor>
  <fsa:ProfitLoss contextRef="Per01072013_30062014_4_Overført_resultat" decimals="0" unitRef="DKK">83625</fsa:ProfitLoss>
  <fsa:ProfitLoss contextRef="Per01072012_30062013_0_Overført_resultat" decimals="0" unitRef="DKK">296343</fsa:ProfitLoss>
</xbrl>