<?xml version="1.0" encoding="utf-8"?>
<!--Generated by EV Revisor version 4.00.9-->
<!--Local version: Report EVRK6.10.03,EV-XBRL / codeunit EVRK6.10.03,EV-XBRL-->
<xbrl xmlns="http://www.xbrl.org/2003/instance" xmlns:link="http://www.xbrl.org/2003/linkbase" xmlns:xlink="http://www.w3.org/1999/xlink" xmlns:iso4217="http://www.xbrl.org/2003/iso4217" xmlns:xbrldi="http://xbrl.org/2006/xbrldi" xmlns:cmn="http://xbrl.dcca.dk/cmn" xmlns:EOGS-EV10000="http://xbrl.dcca.dk/arr" xmlns:EOGS-EV20000="http://xbrl.dcca.dk/dst" xmlns:EOGS-EV30000="http://xbrl.dcca.dk/eogs" xmlns:EOGS-EV40000="http://xbrl.dcca.dk/fsa" xmlns:EOGS-EV50000="http://xbrl.dcca.dk/gsd" xmlns:EOGS-EV60000="http://xbrl.dcca.dk/mrv" xmlns:EOGS-EV70000="http://xbrl.dcca.dk/sob" xmlns:EOGS-EV80000="http://xbrl.dcca.dk/tax"><link:schemaRef xlink:type="simple" xlink:arcrole="http://www.w3.org/1999/xlink/properties/linkbase" xlink:href="http://archprod.service.eogs.dk/taxonomy/20120101/entryDanishGAAPBalanceSheetAccountFormIncomeStatementByNatureIncludingManagementsReviewStatisticsAndTax20120101.xsd"/><context id="nNC0" xmlns="http://www.xbrl.org/2003/instance"><entity xmlns="http://www.xbrl.org/2003/instance"><identifier xmlns="http://www.xbrl.org/2003/instance" scheme="http://www.dcca.dk/cvr">31579805</identifier></entity><period xmlns="http://www.xbrl.org/2003/instance"><startDate xmlns="http://www.xbrl.org/2003/instance">2013-01-01</startDate><endDate xmlns="http://www.xbrl.org/2003/instance">2013-12-31</endDate></period></context><context id="NC1" xmlns="http://www.xbrl.org/2003/instance"><entity xmlns="http://www.xbrl.org/2003/instance"><identifier xmlns="http://www.xbrl.org/2003/instance" scheme="http://www.dcca.dk/cvr">31579805</identifier></entity><period xmlns="http://www.xbrl.org/2003/instance"><startDate xmlns="http://www.xbrl.org/2003/instance">2012-12-01</startDate><endDate xmlns="http://www.xbrl.org/2003/instance">2012-12-31</endDate></period></context><context id="EV1" xmlns="http://www.xbrl.org/2003/instance"><entity xmlns="http://www.xbrl.org/2003/instance"><identifier xmlns="http://www.xbrl.org/2003/instance" scheme="http://www.dcca.dk/cvr">31579805</identifier></entity><period xmlns="http://www.xbrl.org/2003/instance"><instant xmlns="http://www.xbrl.org/2003/instance">2012-12-31</instant></period></context><context id="NC2" xmlns="http://www.xbrl.org/2003/instance"><entity xmlns="http://www.xbrl.org/2003/instance"><identifier xmlns="http://www.xbrl.org/2003/instance" scheme="http://www.dcca.dk/cvr">31579805</identifier></entity><period xmlns="http://www.xbrl.org/2003/instance"><startDate xmlns="http://www.xbrl.org/2003/instance">2013-01-01</startDate><endDate xmlns="http://www.xbrl.org/2003/instance">2013-12-31</endDate></period></context><context id="EV2" xmlns="http://www.xbrl.org/2003/instance"><entity xmlns="http://www.xbrl.org/2003/instance"><identifier xmlns="http://www.xbrl.org/2003/instance" scheme="http://www.dcca.dk/cvr">31579805</identifier></entity><period xmlns="http://www.xbrl.org/2003/instance"><instant xmlns="http://www.xbrl.org/2003/instance">2013-12-31</instant></period></context><unit xmlns="http://www.xbrl.org/2003/instance" id="currency"><measure xmlns="http://www.xbrl.org/2003/instance">iso4217:DKK</measure></unit><EOGS-EV10000:DateOfAuditorsReportOnAuditedFinancialStatements contextRef="nNC0">2014-05-06</EOGS-EV10000:DateOfAuditorsReportOnAuditedFinancialStatements><EOGS-EV10000:OtherReports contextRef="nNC0">Til den daglige ledelse i Malerfirmaet René Jensen ApS   Vi har opstillet årsregnskabet for Malerfirmaet René Jensen ApS  for regnskabsåret 1. januar 2013 - 31. december 2013 på grundlag af selskabets bogføring og øvrige oplysninger, som De har tilvejebragt.  Årsregnskabet omfatter anvendt regnskabspraksis, resultatopgørelse, balance og noter.  </EOGS-EV10000:OtherReports><EOGS-EV10000:DescriptionOfOtherEngagement contextRef="nNC0">Vi har udført opgaven i overensstemmelse med ISRS 4410, Opgaver om opstilling af finansielle oplysninger.  Vi har anvendt vores faglige ekspertise til at assistere Dem med at udarbejde og præsentere årsregnskabet i overensstemmelse med årsregnskabsloven. Vi har overholdt relevante bestemmelser i revisorloven og FSR – danske revisorers Etiske regler for revisorer, herunder principper vedrørende integritet, objektivitet, faglig kompetence og fornøden omhu.  Årsregnskabet samt nøjagtigheden og fuldstændigheden af de oplysninger, der er anvendt til opstillingen af årsregnskabet, er Deres ansvar.  Da en opgave om opstilling af finansielle oplysninger ikke er en erklæringsopgave med sikkerhed, er vi ikke forpligtet til at verificere nøjagtigheden eller fuldstændigheden af de oplysninger, De har givet os til brug for at opstille årsregnskabet. Vi udtrykker derfor ingen revisions- eller reviewkonklusion om, hvorvidt årsregnskabet er udarbejdet i overensstemmelse med årsregnskabsloven.   </EOGS-EV10000:DescriptionOfOtherEngagement><EOGS-EV10000:PlaceOfCompilationOfOtherReport contextRef="nNC0"> Aabybro , den 2014-05-06   </EOGS-EV10000:PlaceOfCompilationOfOtherReport><EOGS-EV10000:NameAndSurnameOfAuditorAppointedToPerformOtherEngagement contextRef="nNC0">Anette Frederiksen  Registreret revisor   </EOGS-EV10000:NameAndSurnameOfAuditorAppointedToPerformOtherEngagement><EOGS-EV10000:NameOfAuditFirmAppointedToPerformOtherEngagement contextRef="nNC0"> Revisor Team Nord  Registreret Revisionsaktieselskab     </EOGS-EV10000:NameOfAuditFirmAppointedToPerformOtherEngagement><EOGS-EV40000:WritedownsOfCurrentAssetsOtherThanCurrentFinancialAssets contextRef="NC1" precision="INF" unitRef="currency">9636</EOGS-EV40000:WritedownsOfCurrentAssetsOtherThanCurrentFinancialAssets><EOGS-EV40000:WritedownsOfCurrentAssetsOtherThanCurrentFinancialAssets contextRef="NC2" precision="INF" unitRef="currency">0</EOGS-EV40000:WritedownsOfCurrentAssetsOtherThanCurrentFinancialAssets><EOGS-EV40000:TaxExpense contextRef="NC1" precision="INF" unitRef="currency">71029</EOGS-EV40000:TaxExpense><EOGS-EV40000:TaxExpense contextRef="NC2" precision="INF" unitRef="currency">55686</EOGS-EV40000:TaxExpense><EOGS-EV40000:ProfitLoss contextRef="NC1" precision="INF" unitRef="currency">205875</EOGS-EV40000:ProfitLoss><EOGS-EV40000:ProfitLoss contextRef="NC2" precision="INF" unitRef="currency">165640</EOGS-EV40000:ProfitLoss><EOGS-EV40000:Goodwill contextRef="EV1" precision="INF" unitRef="currency">250000</EOGS-EV40000:Goodwill><EOGS-EV40000:Goodwill contextRef="EV2" precision="INF" unitRef="currency">200000</EOGS-EV40000:Goodwill><EOGS-EV40000:FixturesFittingsToolsAndEquipment contextRef="EV1" precision="INF" unitRef="currency">114439</EOGS-EV40000:FixturesFittingsToolsAndEquipment><EOGS-EV40000:FixturesFittingsToolsAndEquipment contextRef="EV2" precision="INF" unitRef="currency">696727</EOGS-EV40000:FixturesFittingsToolsAndEquipment><EOGS-EV40000:ShorttermTradeReceivables contextRef="EV1" precision="INF" unitRef="currency">357106</EOGS-EV40000:ShorttermTradeReceivables><EOGS-EV40000:ShorttermTradeReceivables contextRef="EV2" precision="INF" unitRef="currency">258393</EOGS-EV40000:ShorttermTradeReceivables><EOGS-EV40000:OtherShorttermReceivables contextRef="EV1" precision="INF" unitRef="currency">5700</EOGS-EV40000:OtherShorttermReceivables><EOGS-EV40000:OtherShorttermReceivables contextRef="EV2" precision="INF" unitRef="currency">5700</EOGS-EV40000:OtherShorttermReceivables><EOGS-EV40000:ShorttermReceivables contextRef="EV1" precision="INF" unitRef="currency">600510</EOGS-EV40000:ShorttermReceivables><EOGS-EV40000:ShorttermReceivables contextRef="EV2" precision="INF" unitRef="currency">391892</EOGS-EV40000:ShorttermReceivables><EOGS-EV40000:ShorttermReceivablesFromGroupEnterprises contextRef="EV1" precision="INF" unitRef="currency">237704</EOGS-EV40000:ShorttermReceivablesFromGroupEnterprises><EOGS-EV40000:ShorttermReceivablesFromGroupEnterprises contextRef="EV2" precision="INF" unitRef="currency">127799</EOGS-EV40000:ShorttermReceivablesFromGroupEnterprises><EOGS-EV40000:CashAndCashEquivalents contextRef="EV1" precision="INF" unitRef="currency">651868</EOGS-EV40000:CashAndCashEquivalents><EOGS-EV40000:CashAndCashEquivalents contextRef="EV2" precision="INF" unitRef="currency">178102</EOGS-EV40000:CashAndCashEquivalents><EOGS-EV40000:CurrentAssets contextRef="EV1" precision="INF" unitRef="currency">1252378</EOGS-EV40000:CurrentAssets><EOGS-EV40000:CurrentAssets contextRef="EV2" precision="INF" unitRef="currency">569993</EOGS-EV40000:CurrentAssets><EOGS-EV40000:Provisions contextRef="EV1" precision="INF" unitRef="currency">54089</EOGS-EV40000:Provisions><EOGS-EV40000:Provisions contextRef="EV2" precision="INF" unitRef="currency">73050</EOGS-EV40000:Provisions><EOGS-EV40000:ProvisionsForDeferredTax contextRef="EV1" precision="INF" unitRef="currency">54089</EOGS-EV40000:ProvisionsForDeferredTax><EOGS-EV40000:ProvisionsForDeferredTax contextRef="EV2" precision="INF" unitRef="currency">73050</EOGS-EV40000:ProvisionsForDeferredTax><EOGS-EV40000:ShorttermTradePayables contextRef="EV1" precision="INF" unitRef="currency">86185</EOGS-EV40000:ShorttermTradePayables><EOGS-EV40000:ShorttermTradePayables contextRef="EV2" precision="INF" unitRef="currency">49385</EOGS-EV40000:ShorttermTradePayables><EOGS-EV40000:LiabilitiesAndEquity contextRef="EV1" precision="INF" unitRef="currency">1616817</EOGS-EV40000:LiabilitiesAndEquity><EOGS-EV40000:LiabilitiesAndEquity contextRef="EV2" precision="INF" unitRef="currency">1466720</EOGS-EV40000:LiabilitiesAndEquity><EOGS-EV40000:LiabilitiesOtherThanProvisions contextRef="EV1" precision="INF" unitRef="currency">601281</EOGS-EV40000:LiabilitiesOtherThanProvisions><EOGS-EV40000:LiabilitiesOtherThanProvisions contextRef="EV2" precision="INF" unitRef="currency">366583</EOGS-EV40000:LiabilitiesOtherThanProvisions><EOGS-EV40000:DisclosureOfAccountingPolicies contextRef="nNC0">Årsrapporten for Malerfirmaet René Jensen ApS for 2013 er aflagt efter årsregnskabslovens regnskabsklasse B.  Den anvendte regnskabspraksis er uændret i forhold til tidligere år.  RESULTATOPGØRELSEN  Nettoomsætning Nettoomsætning indregnes i resultatopgørelsen, såfremt levering og risikoovergang til køber har fundet sted inden årets udgang.  Finansielle indtægter og omkostninger Finansielle indtægter og omkostninger inkluderer renter.   Skat af årets resultat Årets skat består af årets aktuelle skat og ændringer i årets udskudte skat.   Selskabet er sambeskattet med koncernforbundne selskaber.  BALANCEN  Immaterielle anlægsaktiver Goodwill erhvervet i forbindelse med køb af aktiviteter måles til kostpris med fradrag af akkumulerede af- og nedskrivninger. Goodwill afskrives lineært over den forventede økonomiske brugstid, der er vurderet til 10 år.  Materielle anlægsaktiver Materielle anlægsaktiver måles til kostpris med fradrag af akkumulerede af- og nedskrivninger. Kostpris omfatter anskaffelsesprisen og omkostninger direkte tilknyttet anskaffelsen indtil det tidspunkt, hvor aktivet er klart til at blive taget i brug.  Afskrivningsgrundlaget, der opgøres som kostpris reduceret med eventuel restværdi, fordeles lineært over aktivernes forventede brugstid, der udgør:  Andre anlæg, driftsmateriel og inventar 4 - 7 år  Fortjeneste eller tab ved afhændelse af materielle anlægsaktiver opgøres som forskellen mellem salgspris med fradrag af salgsomkostninger og den regnskabsmæssige værdi på salgstidspunktet. Fortjeneste eller tab indregnes i resultatopgørelsen under afskrivninger.  Tilgodehavender Tilgodehavender måles til amortiseret kostpris, hvilket sædvanligvis svarer til nominel værdi. Værdien reduceres med nedskrivning til imødegåelse af forventede tab.  Udbytte Udbytte, som forventes udbetalt for året, vises som en særskilt post under egenkapitalen.  Udskudte skatteaktiver og -forpligtelser Udskudt skat måles af midlertidige forskelle mellem regnskabs- og skattemæssige værdier af aktiver og forpligtelser.  Udskudte skatteaktiver, herunder skatteværdien af fremførselsberettigede skattemæssige underskud, måles til den værdi, hvortil aktivet forventes at kunne realiseres, enten ved udligning i skat af fremtidig indtjening eller ved modregning i udskudte skatteforpligtelser.  Udskudt skat måles på grundlag af de skatteregler og skattesatser, der med balancedagens lovgivning vil være gældende, når den udskudte skat forventes udløst som aktuel skat. Ændring i udskudt skat som følge af ændringer i skattesatser indregnes i resultatopgørelsen.   Gældsforpligtelser Gældsforpligtelser måles til amortiseret kostpris svarende til nominel restgæld.  </EOGS-EV40000:DisclosureOfAccountingPolicies><EOGS-EV40000:InformationOnReportingClassOfEntity contextRef="nNC0">Regnskabsklasse B</EOGS-EV40000:InformationOnReportingClassOfEntity><EOGS-EV40000:ClassOfReportingEntity contextRef="nNC0">Regnskabsklasse B</EOGS-EV40000:ClassOfReportingEntity><EOGS-EV40000:IntangibleAssetsGross contextRef="EV1" precision="INF" unitRef="currency">250000</EOGS-EV40000:IntangibleAssetsGross><EOGS-EV40000:IntangibleAssetsGross contextRef="EV2" precision="INF" unitRef="currency">200000</EOGS-EV40000:IntangibleAssetsGross><EOGS-EV40000:PropertyPlantAndEquipmentGross contextRef="EV1" precision="INF" unitRef="currency">114439</EOGS-EV40000:PropertyPlantAndEquipmentGross><EOGS-EV40000:PropertyPlantAndEquipmentGross contextRef="EV2" precision="INF" unitRef="currency">696727</EOGS-EV40000:PropertyPlantAndEquipmentGross><EOGS-EV40000:DisclosureOfEquity contextRef="nNC0">&lt;table xmlns="http://www.w3.org/1999/xhtml" style="border: 0pt none;width: 650px; border-collapse: collapse;"&gt;&lt;tbody&gt;&lt;tr&gt;&lt;th style="border: 0pt none; width: 55%;"&gt; &lt;/th&gt;&lt;th style="border: 0pt none; font-weight:bold; width:15%; text-align: right;"&gt;Selskabs- kapital&lt;/th&gt;&lt;th style="border: 0pt none; font-weight:bold; width:15%; text-align: right;"&gt;Overkurs ved emission&lt;/th&gt;&lt;th style="border: 0pt none; font-weight:bold; width:15%; text-align: right;"&gt;Reserve for opskrivninger&lt;/th&gt;&lt;th style="border: 0pt none; font-weight:bold; width:15%; text-align: right;"&gt;Andre reserver&lt;/th&gt;&lt;th style="border: 0pt none; font-weight:bold; width:15%; text-align: right;"&gt;Overført resultat&lt;/th&gt;&lt;th style="border: 0pt none; font-weight:bold; width:15%; text-align: right;"&gt;I alt&lt;/th&gt;&lt;/tr&gt;&lt;tr&gt;&lt;td&gt;Saldo primo&lt;/td&gt;&lt;td style="text-align: right;"&gt;125.000&lt;/td&gt;&lt;td style="text-align: right;"&gt;0&lt;/td&gt;&lt;td style="text-align: right;"&gt;0&lt;/td&gt;&lt;td style="text-align: right;"&gt;0&lt;/td&gt;&lt;td style="text-align: right;"&gt;736.446&lt;/td&gt;&lt;td style="text-align: right;"&gt;861.446&lt;/td&gt;&lt;/tr&gt;&lt;tr&gt;&lt;td&gt;Årets resultat&lt;/td&gt;&lt;td style="text-align: right;"&gt;0&lt;/td&gt;&lt;td style="text-align: right;"&gt;0&lt;/td&gt;&lt;td style="text-align: right;"&gt;0&lt;/td&gt;&lt;td style="text-align: right;"&gt;0&lt;/td&gt;&lt;td style="text-align: right;"&gt;65.640&lt;/td&gt;&lt;td style="text-align: right;"&gt;65.640&lt;/td&gt;&lt;/tr&gt;&lt;tr&gt;&lt;td&gt;Udloddet udbytte&lt;/td&gt;&lt;td style="text-align: right;"&gt;0&lt;/td&gt;&lt;td style="text-align: right;"&gt;0&lt;/td&gt;&lt;td style="text-align: right;"&gt;0&lt;/td&gt;&lt;td style="text-align: right;"&gt;0&lt;/td&gt;&lt;td style="text-align: right;"&gt;100.000&lt;/td&gt;&lt;td style="text-align: right;"&gt;100.000&lt;/td&gt;&lt;/tr&gt;&lt;tr&gt;&lt;td&gt;Saldo ultimo&lt;/td&gt;&lt;td style="text-align: right;"&gt;125.000&lt;/td&gt;&lt;td style="text-align: right;"&gt;0&lt;/td&gt;&lt;td style="text-align: right;"&gt;0&lt;/td&gt;&lt;td style="text-align: right;"&gt;0&lt;/td&gt;&lt;td style="text-align: right;"&gt;902.087&lt;/td&gt;&lt;td style="text-align: right;"&gt;1.027.087&lt;/td&gt;&lt;/tr&gt;&lt;tr&gt;&lt;td&gt;&lt;/td&gt;&lt;td style="text-align: right;"&gt;&lt;/td&gt;&lt;td style="text-align: right;"&gt;&lt;/td&gt;&lt;/tr&gt;&lt;tr&gt;&lt;td&gt;Selskabskapitalen har ikke været ændret i de seneste 5 år.&lt;/td&gt;&lt;td style="text-align: right;"&gt;&lt;/td&gt;&lt;td style="text-align: right;"&gt;&lt;/td&gt;&lt;/tr&gt;&lt;/tbody&gt;&lt;/table&gt;</EOGS-EV40000:DisclosureOfEquity><EOGS-EV40000:RestOfOtherFinanceExpenses contextRef="NC1" precision="INF" unitRef="currency">842</EOGS-EV40000:RestOfOtherFinanceExpenses><EOGS-EV40000:RestOfOtherFinanceExpenses contextRef="NC2" precision="INF" unitRef="currency">727</EOGS-EV40000:RestOfOtherFinanceExpenses><EOGS-EV40000:DisclosureOfTaxExpenses contextRef="nNC0">&lt;table xmlns="http://www.w3.org/1999/xhtml" style="border: 0pt none;width: 650px; border-collapse: collapse;"&gt;&lt;tbody&gt;&lt;tr&gt;&lt;th style="border: 0pt none; width: 55%;"&gt; &lt;/th&gt;&lt;th style="border: 0pt none; font-weight:bold; width:15%; text-align: right;"&gt;2013&lt;/th&gt;&lt;th style="border: 0pt none; font-weight:bold; width:15%; text-align: right;"&gt;2012&lt;/th&gt;&lt;/tr&gt;&lt;tr&gt;&lt;td&gt;Skat af årets resultat&lt;/td&gt;&lt;td style="text-align: right;"&gt;36.725&lt;/td&gt;&lt;td style="text-align: right;"&gt;102.749&lt;/td&gt;&lt;/tr&gt;&lt;tr&gt;&lt;td&gt;Udskudt skat af årets resultat&lt;/td&gt;&lt;td style="text-align: right;"&gt;18.961&lt;/td&gt;&lt;td style="text-align: right;"&gt;-31.720&lt;/td&gt;&lt;/tr&gt;&lt;tr&gt;&lt;td&gt;Skat af årets resultat i alt&lt;/td&gt;&lt;td style="text-align: right;"&gt;55.686&lt;/td&gt;&lt;td style="text-align: right;"&gt;71.029&lt;/td&gt;&lt;/tr&gt;&lt;/tbody&gt;&lt;/table&gt;</EOGS-EV40000:DisclosureOfTaxExpenses><EOGS-EV40000:DisclosureOfEmployeeBenefitsExpense contextRef="nNC0">&lt;table xmlns="http://www.w3.org/1999/xhtml" style="border: 0pt none;width: 650px; border-collapse: collapse;"&gt;&lt;tbody&gt;&lt;tr&gt;&lt;th style="border: 0pt none; width: 55%;"&gt; &lt;/th&gt;&lt;th style="border: 0pt none; font-weight:bold; width:15%; text-align: right;"&gt;2013&lt;/th&gt;&lt;th style="border: 0pt none; font-weight:bold; width:15%; text-align: right;"&gt;2012&lt;/th&gt;&lt;/tr&gt;&lt;tr&gt;&lt;td&gt;Løn, gager og vederlag&lt;/td&gt;&lt;td style="text-align: right;"&gt;1.455.640&lt;/td&gt;&lt;td style="text-align: right;"&gt;1.693.843&lt;/td&gt;&lt;/tr&gt;&lt;tr&gt;&lt;td&gt;Pensionsforpligtelse&lt;/td&gt;&lt;td style="text-align: right;"&gt;246.687&lt;/td&gt;&lt;td style="text-align: right;"&gt;223.081&lt;/td&gt;&lt;/tr&gt;&lt;tr&gt;&lt;td&gt;Andre udgifter til social sikring&lt;/td&gt;&lt;td style="text-align: right;"&gt;80.929&lt;/td&gt;&lt;td style="text-align: right;"&gt;110.088&lt;/td&gt;&lt;/tr&gt;&lt;tr&gt;&lt;td&gt;Personaleomkostninger i alt&lt;/td&gt;&lt;td style="text-align: right;"&gt;1.783.256&lt;/td&gt;&lt;td style="text-align: right;"&gt;2.027.012&lt;/td&gt;&lt;/tr&gt;&lt;/tbody&gt;&lt;/table&gt;</EOGS-EV40000:DisclosureOfEmployeeBenefitsExpense><EOGS-EV40000:EmployeeBenefitsExpense contextRef="NC1" precision="INF" unitRef="currency">2027012</EOGS-EV40000:EmployeeBenefitsExpense><EOGS-EV40000:EmployeeBenefitsExpense contextRef="NC2" precision="INF" unitRef="currency">1783256</EOGS-EV40000:EmployeeBenefitsExpense><EOGS-EV40000:OtherFinanceIncome contextRef="NC1" precision="INF" unitRef="currency">9820</EOGS-EV40000:OtherFinanceIncome><EOGS-EV40000:OtherFinanceIncome contextRef="NC2" precision="INF" unitRef="currency">10214</EOGS-EV40000:OtherFinanceIncome><EOGS-EV40000:ShorttermLiabilitiesOtherThanProvisions contextRef="EV1" precision="INF" unitRef="currency">601281</EOGS-EV40000:ShorttermLiabilitiesOtherThanProvisions><EOGS-EV40000:ShorttermLiabilitiesOtherThanProvisions contextRef="EV2" precision="INF" unitRef="currency">366583</EOGS-EV40000:ShorttermLiabilitiesOtherThanProvisions><EOGS-EV40000:ShorttermTaxPayables contextRef="EV1" precision="INF" unitRef="currency">102749</EOGS-EV40000:ShorttermTaxPayables><EOGS-EV40000:ShorttermTaxPayables contextRef="EV2" precision="INF" unitRef="currency">36725</EOGS-EV40000:ShorttermTaxPayables><EOGS-EV40000:OtherShorttermPayables contextRef="EV1" precision="INF" unitRef="currency">412348</EOGS-EV40000:OtherShorttermPayables><EOGS-EV40000:OtherShorttermPayables contextRef="EV2" precision="INF" unitRef="currency">280474</EOGS-EV40000:OtherShorttermPayables><EOGS-EV50000:DateOfGeneralMeeting contextRef="nNC0">2014-05-23</EOGS-EV50000:DateOfGeneralMeeting><EOGS-EV50000:InformationOnTypeOfSubmittedReport contextRef="nNC0">Årsrapport</EOGS-EV50000:InformationOnTypeOfSubmittedReport><EOGS-EV50000:NameAndSurnameOfChairmanOfGeneralMeeting contextRef="nNC0">René Jensen</EOGS-EV50000:NameAndSurnameOfChairmanOfGeneralMeeting><EOGS-EV50000:IdentificationNumberCvrOfSubmittingEnterprise contextRef="nNC0">31579805</EOGS-EV50000:IdentificationNumberCvrOfSubmittingEnterprise><EOGS-EV50000:NameOfSubmittingEnterprise contextRef="nNC0">Malerfirmaet René Jensen ApS</EOGS-EV50000:NameOfSubmittingEnterprise><EOGS-EV50000:AddressOfSubmittingEnterpriseStreetAndNumber contextRef="nNC0">Industrivej 10</EOGS-EV50000:AddressOfSubmittingEnterpriseStreetAndNumber><EOGS-EV50000:AddressOfSubmittingEnterprisePostcodeAndTown contextRef="nNC0">9440Aabybro</EOGS-EV50000:AddressOfSubmittingEnterprisePostcodeAndTown><EOGS-EV50000:DateOfApprovalOfReport contextRef="nNC0">2014-05-06</EOGS-EV50000:DateOfApprovalOfReport><EOGS-EV50000:NameOfFinancialInstitution contextRef="nNC0">Pengeinstitut  Nørresundby Bank ,      </EOGS-EV50000:NameOfFinancialInstitution><EOGS-EV60000:DescriptionOfPrimaryActivitiesOfEntity contextRef="nNC0">&lt;table xmlns="http://www.w3.org/1999/xhtml" style="border: 0pt none;width: 650px; border-collapse: collapse;"&gt;&lt;tbody&gt;&lt;tr&gt;&lt;th style="border: 0pt none; width: 55%;"&gt; &lt;/th&gt;&lt;th style="border: 0pt none; font-weight:bold; width:15%; text-align: right;"&gt;&lt;/th&gt;&lt;th style="border: 0pt none; font-weight:bold; width:15%; text-align: right;"&gt;&lt;/th&gt;&lt;/tr&gt;&lt;tr&gt;&lt;td&gt;Selskabets vigtigste forretningsområde er drift af malervirksomhed.&lt;/td&gt;&lt;td style="text-align: right;"&gt;&lt;/td&gt;&lt;td style="text-align: right;"&gt;&lt;/td&gt;&lt;/tr&gt;&lt;/tbody&gt;&lt;/table&gt;</EOGS-EV60000:DescriptionOfPrimaryActivitiesOfEntity><EOGS-EV40000:GrossProfitLoss contextRef="NC1" precision="INF" unitRef="currency">2480817</EOGS-EV40000:GrossProfitLoss><EOGS-EV40000:GrossProfitLoss contextRef="NC2" precision="INF" unitRef="currency">2112808</EOGS-EV40000:GrossProfitLoss><EOGS-EV40000:DepreciationAmortisationExpenseAndImpairmentLossesOfPropertyPlantAndEquipmentAndIntangibleAssets contextRef="NC1" precision="INF" unitRef="currency">176242</EOGS-EV40000:DepreciationAmortisationExpenseAndImpairmentLossesOfPropertyPlantAndEquipmentAndIntangibleAssets><EOGS-EV40000:DepreciationAmortisationExpenseAndImpairmentLossesOfPropertyPlantAndEquipmentAndIntangibleAssets contextRef="NC2" precision="INF" unitRef="currency">117712</EOGS-EV40000:DepreciationAmortisationExpenseAndImpairmentLossesOfPropertyPlantAndEquipmentAndIntangibleAssets><EOGS-EV70000:StatementByExecutiveAndSupervisoryBoards contextRef="nNC0">Ledelsen har dags dato aflagt årsrapporten for 2013 for Malerfirmaet René Jensen ApS  .  Årsrapporten er aflagt i overensstemmelse med årsregnskabsloven.  Det er vores opfattelse, at årsregnskabet giver et retvisende billede af selskabets aktiver, passiver og finansielle stilling samt af resultatet af selskabets aktiviteter.  Selskabet opfylder betingelserne for ikke at blive revideret.  Årsrapporten indstilles til generalforsamlingens godkendelse.   Aabybro , den 2014-05-06     Direktion     René Jensen,         </EOGS-EV70000:StatementByExecutiveAndSupervisoryBoards><EOGS-EV70000:DateOfApprovalOfAnnualReport contextRef="nNC0">2014-05-06</EOGS-EV70000:DateOfApprovalOfAnnualReport><EOGS-EV40000:Assets contextRef="EV1" precision="INF" unitRef="currency">1616817</EOGS-EV40000:Assets><EOGS-EV40000:Assets contextRef="EV2" precision="INF" unitRef="currency">1466720</EOGS-EV40000:Assets><EOGS-EV50000:IdentificationNumberCvrOfReportingEntity contextRef="nNC0">31579805</EOGS-EV50000:IdentificationNumberCvrOfReportingEntity><EOGS-EV40000:ProfitLossFromOrdinaryOperatingActivities contextRef="NC1" precision="INF" unitRef="currency">267927</EOGS-EV40000:ProfitLossFromOrdinaryOperatingActivities><EOGS-EV40000:ProfitLossFromOrdinaryOperatingActivities contextRef="NC2" precision="INF" unitRef="currency">211840</EOGS-EV40000:ProfitLossFromOrdinaryOperatingActivities><EOGS-EV40000:NoncurrentAssets contextRef="EV1" precision="INF" unitRef="currency">364439</EOGS-EV40000:NoncurrentAssets><EOGS-EV40000:NoncurrentAssets contextRef="EV2" precision="INF" unitRef="currency">896727</EOGS-EV40000:NoncurrentAssets><EOGS-EV40000:Equity contextRef="EV1" precision="INF" unitRef="currency">961446</EOGS-EV40000:Equity><EOGS-EV40000:Equity contextRef="EV2" precision="INF" unitRef="currency">1027087</EOGS-EV40000:Equity><EOGS-EV40000:ContributedCapital contextRef="EV1" precision="INF" unitRef="currency">125000</EOGS-EV40000:ContributedCapital><EOGS-EV40000:ContributedCapital contextRef="EV2" precision="INF" unitRef="currency">125000</EOGS-EV40000:ContributedCapital><EOGS-EV40000:RetainedEarnings contextRef="EV1" precision="INF" unitRef="currency">736446</EOGS-EV40000:RetainedEarnings><EOGS-EV40000:RetainedEarnings contextRef="EV2" precision="INF" unitRef="currency">802087</EOGS-EV40000:RetainedEarnings><EOGS-EV40000:ProposedDividendRecognisedInEquity contextRef="EV1" precision="INF" unitRef="currency">100000</EOGS-EV40000:ProposedDividendRecognisedInEquity><EOGS-EV40000:ProposedDividendRecognisedInEquity contextRef="EV2" precision="INF" unitRef="currency">100000</EOGS-EV40000:ProposedDividendRecognisedInEquity><EOGS-EV50000:NameOfReportingEntity contextRef="nNC0">Malerfirmaet René Jensen ApS</EOGS-EV50000:NameOfReportingEntity><EOGS-EV50000:AddressOfReportingEntityStreetAndNumber contextRef="nNC0">Porsevej 11</EOGS-EV50000:AddressOfReportingEntityStreetAndNumber><EOGS-EV50000:AddressOfReportingEntityPostcodeAndTown contextRef="nNC0">9440Aabybro</EOGS-EV50000:AddressOfReportingEntityPostcodeAndTown><EOGS-EV50000:RegisteredOfficeOfReportingEntity contextRef="nNC0">Jammerbugt Kommune</EOGS-EV50000:RegisteredOfficeOfReportingEntity><EOGS-EV50000:ReportingPeriodStartDate contextRef="nNC0">2013-01-01</EOGS-EV50000:ReportingPeriodStartDate><EOGS-EV50000:ReportingPeriodEndDate contextRef="nNC0">2013-12-31</EOGS-EV50000:ReportingPeriodEndDate></xbrl>
