<?xml version="1.0" encoding="utf-8"?><!--Dette XBRL instansdokument er genereret af IT Revisor (5.4.10.0) - http://www.focus-it.dk/it-revisor.aspx--><xbrl xmlns="http://www.xbrl.org/2003/instance" xmlns:mrv="http://xbrl.dcca.dk/mrv" xmlns:arr="http://xbrl.dcca.dk/arr" xmlns:fsa="http://xbrl.dcca.dk/fsa" xmlns:sob="http://xbrl.dcca.dk/sob" xmlns:gsd="http://xbrl.dcca.dk/gsd" xmlns:tax="http://xbrl.dcca.dk/tax" xmlns:dst="http://xbrl.dcca.dk/dst" xmlns:cmn="http://xbrl.dcca.dk/cmn" xmlns:eogs="http://xbrl.dcca.dk/eogs" xmlns:iso4217="http://www.xbrl.org/2003/iso4217" xmlns:xlink="http://www.w3.org/1999/xlink" xmlns:link="http://www.xbrl.org/2003/linkbase" xmlns:xbrldi="http://xbrl.org/2006/xbrldi"><link:schemaRef xlink:type="simple" xlink:href="http://archprod.service.eogs.dk/taxonomy/20130401/entryDanishGAAPBalanceSheetReportFormIncomeStatementByNatureIncludingManagementsReviewStatisticsAndTax20130401.xsd" /><context id="Per01102012_30092013"><entity><identifier scheme="http://www.dcca.dk/cvr">32878466</identifier></entity><period><startDate>2012-10-01</startDate><endDate>2013-09-30</endDate></period></context><context id="Per01102011_30092012"><entity><identifier scheme="http://www.dcca.dk/cvr">32878466</identifier></entity><period><startDate>2011-10-01</startDate><endDate>2012-09-30</endDate></period></context><context id="Per01102012_30092013-Instant"><entity><identifier scheme="http://www.dcca.dk/cvr">32878466</identifier></entity><period><instant>2013-09-30</instant></period></context><context id="Per01102011_30092012-Instant"><entity><identifier scheme="http://www.dcca.dk/cvr">32878466</identifier></entity><period><instant>2012-09-30</instant></period></context><context id="Per01102012_30092013_0_Identifikation_af_medlem_af_direktionen"><entity><identifier scheme="http://www.dcca.dk/cvr">32878466</identifier></entity><period><startDate>2012-10-01</startDate><endDate>2013-09-30</endDate></period><scenario><xbrldi:typedMember dimension="cmn:IdentificationOfMemberOfExecutiveBoardDimension"><cmn:memberOfBoardIdentifier>0</cmn:memberOfBoardIdentifier></xbrldi:typedMember></scenario></context><context id="Per01102012_30092013_1_Identifikation_af_revisor"><entity><identifier scheme="http://www.dcca.dk/cvr">32878466</identifier></entity><period><startDate>2012-10-01</startDate><endDate>2013-09-30</endDate></period><scenario><xbrldi:typedMember dimension="cmn:IdentificationOfAuditorDimension"><cmn:auditorIdentifier>1</cmn:auditorIdentifier></xbrldi:typedMember></scenario></context><context id="Per01102012_30092013_2_Foreslået_udbytte_indregnet_under_gældsforpligtelser"><entity><identifier scheme="http://www.dcca.dk/cvr">32878466</identifier></entity><period><startDate>2012-10-01</startDate><endDate>2013-09-30</endDate></period><scenario><xbrldi:explicitMember dimension="fsa:ResultDistributionDimension">fsa:ProposedDividendRecognisedInLiabilitiesMember</xbrldi:explicitMember></scenario></context><context id="Per01102012_30092013_3_Overført_resultat"><entity><identifier scheme="http://www.dcca.dk/cvr">32878466</identifier></entity><period><startDate>2012-10-01</startDate><endDate>2013-09-30</endDate></period><scenario><xbrldi:explicitMember dimension="fsa:ResultDistributionDimension">fsa:RetainedEarningsMember</xbrldi:explicitMember></scenario></context><context id="Per01102011_30092012_0_Foreslået_udbytte_indregnet_under_gældsforpligtelser"><entity><identifier scheme="http://www.dcca.dk/cvr">32878466</identifier></entity><period><startDate>2011-10-01</startDate><endDate>2012-09-30</endDate></period><scenario><xbrldi:explicitMember dimension="fsa:ResultDistributionDimension">fsa:ProposedDividendRecognisedInLiabilitiesMember</xbrldi:explicitMember></scenario></context><context id="Per01102011_30092012_1_Overført_resultat"><entity><identifier scheme="http://www.dcca.dk/cvr">32878466</identifier></entity><period><startDate>2011-10-01</startDate><endDate>2012-09-30</endDate></period><scenario><xbrldi:explicitMember dimension="fsa:ResultDistributionDimension">fsa:RetainedEarningsMember</xbrldi:explicitMember></scenario></context><unit id="DKK"><measure>iso4217:DKK</measure></unit><unit id="shares"><measure>shares</measure></unit><unit id="pure"><measure>pure</measure></unit><gsd:DateOfGeneralMeeting contextRef="Per01102012_30092013">2014-02-28</gsd:DateOfGeneralMeeting><gsd:NameAndSurnameOfChairmanOfGeneralMeeting contextRef="Per01102012_30092013">Casper Holm Nielsen</gsd:NameAndSurnameOfChairmanOfGeneralMeeting><arr:SignatureOfAuditorsPlace contextRef="Per01102012_30092013">Rønne</arr:SignatureOfAuditorsPlace><arr:SignatureOfAuditorsDate contextRef="Per01102012_30092013">2014-02-28</arr:SignatureOfAuditorsDate><sob:PlaceOfSignatureOfStatement contextRef="Per01102012_30092013">Rønne</sob:PlaceOfSignatureOfStatement><sob:DateOfApprovalOfAnnualReport contextRef="Per01102012_30092013">2014-02-28</sob:DateOfApprovalOfAnnualReport><fsa:ClassOfReportingEntity contextRef="Per01102012_30092013">Regnskabsklasse B</fsa:ClassOfReportingEntity><fsa:SelectedElementsFromReportingClassC contextRef="Per01102012_30092013">false</fsa:SelectedElementsFromReportingClassC><fsa:SelectedElementsFromReportingClassD contextRef="Per01102012_30092013">false</fsa:SelectedElementsFromReportingClassD><cmn:TypeOfAuditorAssistance contextRef="Per01102012_30092013">Revisionspåtegning</cmn:TypeOfAuditorAssistance><gsd:InformationOnTypeOfSubmittedReport contextRef="Per01102012_30092013">Årsrapport</gsd:InformationOnTypeOfSubmittedReport><gsd:IdentificationNumberCvrOfReportingEntity contextRef="Per01102012_30092013">32878466</gsd:IdentificationNumberCvrOfReportingEntity><gsd:NameOfReportingEntity contextRef="Per01102012_30092013">Maler og Gulv Firma ApS</gsd:NameOfReportingEntity><gsd:AddressOfReportingEntityStreetName contextRef="Per01102012_30092013">Smallesund 10</gsd:AddressOfReportingEntityStreetName><gsd:AddressOfReportingEntityPostCodeIdentifier contextRef="Per01102012_30092013">3700</gsd:AddressOfReportingEntityPostCodeIdentifier><gsd:AddressOfReportingEntityDistrictName contextRef="Per01102012_30092013">Rønne</gsd:AddressOfReportingEntityDistrictName><gsd:DateOfFoundationOfReportingEntity contextRef="Per01102012_30092013">2010-04-16</gsd:DateOfFoundationOfReportingEntity><gsd:RegisteredOfficeOfReportingEntity contextRef="Per01102012_30092013">Bornholms Regionskommune</gsd:RegisteredOfficeOfReportingEntity><gsd:TelephoneNumberOfReportingEntity contextRef="Per01102012_30092013">56 95 84 30</gsd:TelephoneNumberOfReportingEntity><gsd:HomepageOfReportingEntity contextRef="Per01102012_30092013">www.casperholmnielsen.dk</gsd:HomepageOfReportingEntity><gsd:EmailOfReportingEntity contextRef="Per01102012_30092013">mail@casperholmnielsen.dk</gsd:EmailOfReportingEntity><gsd:NameOfFinancialInstitution contextRef="Per01102012_30092013">Sydbank</gsd:NameOfFinancialInstitution><gsd:ReportingPeriodStartDate contextRef="Per01102012_30092013">2012-10-01</gsd:ReportingPeriodStartDate><gsd:ReportingPeriodEndDate contextRef="Per01102012_30092013">2013-09-30</gsd:ReportingPeriodEndDate><gsd:NameOfSubmittingEnterprise contextRef="Per01102012_30092013">Rønne Revision,</gsd:NameOfSubmittingEnterprise><gsd:AddressOfSubmittingEnterpriseStreetAndNumber contextRef="Per01102012_30092013">Store Torvegade 12, 1</gsd:AddressOfSubmittingEnterpriseStreetAndNumber><gsd:AddressOfSubmittingEnterprisePostcodeAndTown contextRef="Per01102012_30092013">3700, Rønne</gsd:AddressOfSubmittingEnterprisePostcodeAndTown><sob:IdentificationOfApprovedAnnualReport contextRef="Per01102012_30092013">Direktionen har dags dato behandlet og godkendt årsrapporten for perioden 1. oktober 2012 - 30. september 2013 for Maler og Gulv Firma ApS.</sob:IdentificationOfApprovedAnnualReport><sob:ConfirmationThatAnnualReportIsPresentedInAccordanceWithRequirementsProvidedForByLegislationAnyStandardsAndRequirementsProvidedByArticlesOfAssociationOrByAgreement contextRef="Per01102012_30092013">Årsrapporten aflægges i overensstemmelse med årsregnskabsloven.</sob:ConfirmationThatAnnualReportIsPresentedInAccordanceWithRequirementsProvidedForByLegislationAnyStandardsAndRequirementsProvidedByArticlesOfAssociationOrByAgreement><sob:ConfirmationThatFinancialStatementGivesTrueAndFairViewOfAssetsLiabilitiesEquityFinancialPositionAndResults contextRef="Per01102012_30092013">Det er min opfattelse, at årsregnskabet giver et retvisende billede af selskabets aktiver, passiver og finansielle stilling pr. 30. september 2013 samt af resultatet af selskabets aktiviteter for perioden 1. oktober 2012 - 30. september 2013.</sob:ConfirmationThatFinancialStatementGivesTrueAndFairViewOfAssetsLiabilitiesEquityFinancialPositionAndResults><sob:ManagementsStatementAboutManagementsReview contextRef="Per01102012_30092013">Ledelsesberetningen indeholder efter min opfattelse en retvisende redegørelse for de forhold, beretningen omhandler.</sob:ManagementsStatementAboutManagementsReview><sob:RecommendationForApprovalOfAnnualReportByGeneralMeeting contextRef="Per01102012_30092013">Årsrapporten indstilles til generalforsamlingens godkendelse.</sob:RecommendationForApprovalOfAnnualReportByGeneralMeeting><arr:AddresseeOfAuditorsReportOnReviewOfFinancialStatements contextRef="Per01102012_30092013">Til kapitalejerne af Maler og Gulv Firma ApS</arr:AddresseeOfAuditorsReportOnReviewOfFinancialStatements><arr:IdentificationOfAuditedFinancialStatements contextRef="Per01102012_30092013">Vi har revideret årsregnskabet for Maler og Gulv Firma ApS for regnskabsåret 1. oktober 2012 - 30. september 2013, der omfatter anvendt regnskabspraksis, resultatopgørelse, balance, egenkapitalopgørelse og noter. Årsregnskabet udarbejdes efter årsregnskabsloven.</arr:IdentificationOfAuditedFinancialStatements><arr:StatementOfExecutiveAndSupervisoryBoardsResponsibilityForFinancialStatements contextRef="Per01102012_30092013">Ledelsens ansvar for årsregnskabet&lt;br xmlns="http://www.w3.org/1999/xhtml"/&gt;Ledelsen har ansvaret for udarbejdelsen af et årsregnskab, der giver et retvisende billede i overensstemmelse med årsregnskabsloven. Ledelsen har endvidere ansvaret for den interne kontrol, som ledelsen anser nødvendig for at udarbejde et årsregnskab uden væsentlig fejlinformation, uanset om denne skyldes besvigelser eller fejl.</arr:StatementOfExecutiveAndSupervisoryBoardsResponsibilityForFinancialStatements><arr:StatementOfAuditorsResponsibilityForAuditAndAuditPerformed contextRef="Per01102012_30092013">Revisors ansvar&lt;br xmlns="http://www.w3.org/1999/xhtml"/&gt;Vores ansvar er at udtrykke en konklusion om årsregnskabet på grundlag af vores revision. Vi har udført revisionen i overensstemmelse med internationale standarder om revision og yderligere krav ifølge dansk revisorlovgivning. Dette kræver, at vi overholder etiske krav samt planlægger og udfører revisionen for at opnå høj grad af sikkerhed for, om årsregnskabet er uden væsentlig fejlinformation.En revision omfatter udførelse af revisionshandlinger for at opnå revisionsbevis for beløb og oplysninger i årsregnskabet. De valgte revisionshandlinger afhænger af revisors vurdering, herunder vurdering af risici for væsentlig fejlinformation i årsregnskabet, uanset om denne skyldes besvigelser eller fejl. Ved risikovurderingen overvejer revisor intern kontrol, der er relevant for virksomhedens udarbejdelse af et årsregnskab, der giver et retvisende billede. Formålet hermed er at udforme revisionshandlinger, der er passende efter omstændighederne, men ikke at udtrykke en konklusion om effektiviteten af virksomhedens interne kontrol. En revision omfatter endvidere vurdering af, om ledelsens valg af regnskabspraksis er passende, om ledelsens regnskabsmæssige skøn er rimelige samt den samlede præsentation af årsregnskabet.&lt;br xmlns="http://www.w3.org/1999/xhtml"/&gt;Det er vores opfattelse, at det opnåede revisionsbevis er tilstrækkeligt og egnet som grundlag for vor konklusion.Revisionen har ikke givet anledning til forbehold.</arr:StatementOfAuditorsResponsibilityForAuditAndAuditPerformed><arr:OpinionOnAuditedFinancialStatements contextRef="Per01102012_30092013">Konklusion&lt;br xmlns="http://www.w3.org/1999/xhtml"/&gt;Det er vores opfattelse, at årsregnskabet giver et retvisende billede af selskabets aktiver, passiver og finansielle stilling pr. 30. september 2013 samt af resultatet af selskabets aktiviteter for perioden 1. oktober 2012 - 30. september 2013 i overensstemmelse med årsregnskabsloven.</arr:OpinionOnAuditedFinancialStatements><arr:StatementOnManagementsReviewAuditorsReportOnAuditedFinancialStatements contextRef="Per01102012_30092013">Udtalelse om ledelsesberetningen&lt;br xmlns="http://www.w3.org/1999/xhtml"/&gt;Vi har i henhold til årsregnskabsloven gennemlæst ledelsesberetningen. Vi har ikke foretaget yderligere handlinger i tillæg til den udførte revision af årsregnskabet. Det er på denne baggrund vores opfattelse, at oplysningerne i ledelsesberetningen er i overensstemmelse med årsregnskabet.</arr:StatementOnManagementsReviewAuditorsReportOnAuditedFinancialStatements><mrv:DescriptionOfPrimaryActivitiesOfEntity contextRef="Per01102012_30092013">Selskabets hovedaktivitet&lt;br xmlns="http://www.w3.org/1999/xhtml"/&gt;Selskabets forretningsområde er maler- og gulvvirksomhed.</mrv:DescriptionOfPrimaryActivitiesOfEntity><mrv:DescriptionOfAnyUnusualMattersAffectingRecognitionOrMeasurement contextRef="Per01102012_30092013">Usædvanlige forhold&lt;br xmlns="http://www.w3.org/1999/xhtml"/&gt;Der har ingen særlige forhold været, som skønnes at have påvirket årets samlede resultat.</mrv:DescriptionOfAnyUnusualMattersAffectingRecognitionOrMeasurement><mrv:DescriptionOfAnyUncertaintyConnectedWithRecognitionOrMeasurement contextRef="Per01102012_30092013">Usikkerhed ved indregning og måling&lt;br xmlns="http://www.w3.org/1999/xhtml"/&gt;Der er ingen væsentlige usikkerheder ved indregning og måling.</mrv:DescriptionOfAnyUncertaintyConnectedWithRecognitionOrMeasurement><mrv:DescriptionOfDevelopmentInActivitiesAndFinancialAffairs contextRef="Per01102012_30092013">Udviklingen i selskabets aktiviteter og økonomiske forhold&lt;br xmlns="http://www.w3.org/1999/xhtml"/&gt;Årets resultat udgør t.kr. 484, hvilket anses for at være tilfredsstillende.Selskabets balance udviser en samlet aktivmasse på t.kr. 2.599, og en egenkapital på t.kr. 1.370.</mrv:DescriptionOfDevelopmentInActivitiesAndFinancialAffairs><mrv:DescriptionOfSignificantEventsOccurringAfterEndOfReportingPeriod contextRef="Per01102012_30092013">Betydningsfulde hændelser indtruffet efter statusdag&lt;br xmlns="http://www.w3.org/1999/xhtml"/&gt;Der er efter regnskabsårets afslutning ikke indtruffet begivenheder, som væsentligt vil kunne påvirke selskabets finansielle stilling.Den forventede udvikling i regnskabsåret 2013/14Der forventes en uændret aktivitet og indtjening for regnskabsåret 2013/14.</mrv:DescriptionOfSignificantEventsOccurringAfterEndOfReportingPeriod><fsa:InformationOnReportingClassOfEntity contextRef="Per01102012_30092013">GENERELTÅrsregnskabet for Maler og Gulv Firma ApS for 2012/13 er udarbejdet i overensstemmelse med årsregnskabslovens bestemmelser for selskaber i regnskabsklasse B.&lt;br xmlns="http://www.w3.org/1999/xhtml"/&gt;Årsregnskabet aflægges i danske kroner.</fsa:InformationOnReportingClassOfEntity><fsa:DescriptionOfGeneralMattersRelatedToRecognitionMeasurementAndChangesInAccountingPolicies contextRef="Per01102012_30092013">Generelt om indregning og måling&lt;br xmlns="http://www.w3.org/1999/xhtml"/&gt;Indtægter indregnes i resultatopgørelsen i takt med at de indtjenes. Herudover indregnes værdireguleringer af finansielle aktiver og forpligtelser, der måles til dagsværdi eller amortiseret kostpris. Endvidere indregnes i resultatopgørelsen alle omkostninger, der er afholdt for at opnå årets indtjening, herunder afskrivninger, nedskrivninger og hensatte forpligtelser samt tilbageførsler som følge af ændrede regnskabsmæssige skøn af beløb, der tidligere har været indregnet i resultatopgørelsen.&lt;br xmlns="http://www.w3.org/1999/xhtml"/&gt;Aktiver indregnes i balancen, når det er sandsynligt at fremtidige økonomiske fordele vil tilflyde selskabet, og aktivets værdi kan måles pålideligt.&lt;br xmlns="http://www.w3.org/1999/xhtml"/&gt;Forpligtelser indregnes i balancen, når det er sandsynligt, at fremtidige økonomiske fordele vil fragå selskabet, og forpligtelsens værdi kan måles pålideligt.&lt;br xmlns="http://www.w3.org/1999/xhtml"/&gt;Ved indregning og måling tages hensyn til forudsigelige tab og risici, der fremkommer, inden årsregnskabet aflægges, og som be- eller afkræfter forhold, der eksisterer på balancedagen.</fsa:DescriptionOfGeneralMattersRelatedToRecognitionMeasurementAndChangesInAccountingPolicies><fsa:DescriptionOfMethodsOfRecognitionAndMeasurementBasisOfIncomeStatementItems contextRef="Per01102012_30092013">RESULTATOPGØRELSEN</fsa:DescriptionOfMethodsOfRecognitionAndMeasurementBasisOfIncomeStatementItems><fsa:DescriptionOfMethodsOfRecognitionAndMeasurementBasisOfRevenue contextRef="Per01102012_30092013">Igangværende arbejder for fremmed regning vedrørende entreprisekontrakter indregnes i takt med, at produktionen udføres, hvorved nettoomsætningen svarer til salgsværdien af årets udførte arbejde.</fsa:DescriptionOfMethodsOfRecognitionAndMeasurementBasisOfRevenue><fsa:DescriptionOfMethodsOfRecognitionAndMeasurementBasisOfTaxExpenses contextRef="Per01102012_30092013">Skat af årets resultatÅrets skat, som består af årets aktuelle skat og forskydning i udskudt skat, indregnes i resultatopgørelsen med den del, der kan henføres til årets resultat, og direkte på egenkapitalen med den del, der kan henføres til posteringer direkte på egenkapitalen.</fsa:DescriptionOfMethodsOfRecognitionAndMeasurementBasisOfTaxExpenses><fsa:DescriptionOfMethodsOfRecognitionAndMeasurementBasisOfAssetsAndLiabilities contextRef="Per01102012_30092013">BALANCEN</fsa:DescriptionOfMethodsOfRecognitionAndMeasurementBasisOfAssetsAndLiabilities><fsa:DescriptionOfMethodsOfRecognitionAndMeasurementBasisOfPropertyPlantAndEquipment contextRef="Per01102012_30092013">Materielle anlægsaktiver&lt;br xmlns="http://www.w3.org/1999/xhtml"/&gt;Materielle anlægsaktiver måles til kostpris med fradrag af akkumulerede af- og nedskrivninger.&lt;br xmlns="http://www.w3.org/1999/xhtml"/&gt;Afskrivningsgrundlaget er kostpris med fradrag af forventet restværdi efter afsluttet brugstid.Der foretages lineære afskrivninger baseret på følgende vurdering af aktivernes forventede brugstider og restværdier:&lt;br xmlns="http://www.w3.org/1999/xhtml"/&gt;BrugstidDriftsmateriel5 år&lt;br xmlns="http://www.w3.org/1999/xhtml"/&gt;Fortjeneste eller tab ved afhændelse af materielle anlægsaktiver opgøres som forskellen mellem salgspris med fradrag af salgsomkostninger og den regnskabsmæssige værdi på salgstidspunktet. Fortjeneste eller tab indregnes i resultatopgørelsen under andre driftsindtægter/andre driftsomkostninger.</fsa:DescriptionOfMethodsOfRecognitionAndMeasurementBasisOfPropertyPlantAndEquipment><fsa:DescriptionOfMethodsOfRecognitionAndMeasurementBasisOfInventories contextRef="Per01102012_30092013">Varebeholdninger&lt;br xmlns="http://www.w3.org/1999/xhtml"/&gt;Varebeholdninger måles til kostpris efter FIFO-metoden. I tilfælde, hvor nettorealisationsværdien er lavere end kostprisen, nedskrives til denne lavere værdi.</fsa:DescriptionOfMethodsOfRecognitionAndMeasurementBasisOfInventories><fsa:DescriptionOfMethodsOfRecognitionAndMeasurementBasisOfReceivables contextRef="Per01102012_30092013">TilgodehavenderTilgodehavender måles til amortiseret kostpris, hvilket sædvanligvis svarer til nominel værdi. Værdien reduceres med nedskrivning til imødegåelse af forventede tab.&lt;br xmlns="http://www.w3.org/1999/xhtml"/&gt;Nedskrivninger til tab opgøres på grundlag af en individuel vurdering af de enkelte tilgodehavender.</fsa:DescriptionOfMethodsOfRecognitionAndMeasurementBasisOfReceivables><fsa:DescriptionOfMethodsOfRecognitionAndMeasurementBasisOfContractWorkInProgress contextRef="Per01102012_30092013">Igangværende arbejder for fremmed regningIgangværende arbejder for fremmed regning måles til salgsværdien af det udførte arbejde. Salgsværdien måles på baggrund af færdiggørelsesgraden på balancedagen og de samlede forventede indtægter på det enkelte igangværende arbejde.</fsa:DescriptionOfMethodsOfRecognitionAndMeasurementBasisOfContractWorkInProgress><fsa:DescriptionOfMethodsOfRecognitionAndMeasurementBasisOfTaxPayablesAndDeferredTax contextRef="Per01102012_30092013">Selskabsskat og udskudt skatAktuelle skatteforpligtelser og tilgodehavende aktuel skat indregnes i balancen som beregnet skat af årets skattepligtige indkomst reguleret for skat af tidligere års skattepligtige indkomster samt for betalte acontoskatter.Udskudt skat måles efter den balanceorienterede gældsmetode af midlertidige forskelle mellem regnskabsmæssig og skattemæssig værdi af aktiver og forpligtelser. I de tilfælde, f.eks. vedrørende aktier, hvor opgørelse af skatteværdien kan foretages efter alternative beskatningsregler, måles udskudt skat på grundlag af den planlagte anvendelse af aktivet henholdsvis afvikling af forpligtelsen.Udskudte skatteaktiver, herunder skatteværdien af fremførselsberettiget skattemæssigt underskud, måles til den værdi, hvortil aktivet forventes at kunne realiseres, enten ved udligning i skat af fremtidig indtjening eller ved modregning i udskudte skatteforpligtelser inden for samme juridiske skatteenhed. Eventuelle udskudte nettoskatteaktiver måles til nettorealisationsværdi.&lt;br xmlns="http://www.w3.org/1999/xhtml"/&gt;Udskudt skat måles på grundlag af de skatteregler og skattesatser, der med balancedagens lovgivning vil være gældende, når den udskudte skat forventes udløst som aktuel skat. Ændring i udskudt skat som følge af ændringer i skattesatser indregnes i resultatopgørelsen.</fsa:DescriptionOfMethodsOfRecognitionAndMeasurementBasisOfTaxPayablesAndDeferredTax><fsa:DescriptionOfMethodsOfRecognitionAndMeasurementBasisOfLiabilitiesOtherThanProvisions contextRef="Per01102012_30092013">Gældsforpligtelser&lt;br xmlns="http://www.w3.org/1999/xhtml"/&gt;Andre gældsforpligtelser, som omfatter gæld til leverandører samt anden gæld, måles til nominel værdi.</fsa:DescriptionOfMethodsOfRecognitionAndMeasurementBasisOfLiabilitiesOtherThanProvisions><fsa:GrossProfitLoss contextRef="Per01102012_30092013" decimals="0" unitRef="DKK">3661349</fsa:GrossProfitLoss><fsa:EmployeeBenefitsExpense contextRef="Per01102012_30092013" decimals="0" unitRef="DKK">2899464</fsa:EmployeeBenefitsExpense><fsa:DepreciationAmortisationExpenseAndImpairmentLossesOfPropertyPlantAndEquipmentAndIntangibleAssetsRecognisedInProfitOrLoss contextRef="Per01102012_30092013" decimals="0" unitRef="DKK">124029</fsa:DepreciationAmortisationExpenseAndImpairmentLossesOfPropertyPlantAndEquipmentAndIntangibleAssetsRecognisedInProfitOrLoss><fsa:OtherOperatingExpenses contextRef="Per01102012_30092013" decimals="0" unitRef="DKK">0</fsa:OtherOperatingExpenses><fsa:ProfitLossFromOrdinaryOperatingActivities contextRef="Per01102012_30092013" decimals="0" unitRef="DKK">637856</fsa:ProfitLossFromOrdinaryOperatingActivities><fsa:OtherFinanceIncome contextRef="Per01102012_30092013" decimals="0" unitRef="DKK">20785</fsa:OtherFinanceIncome><fsa:RestOfOtherFinanceExpenses contextRef="Per01102012_30092013" decimals="0" unitRef="DKK">12131</fsa:RestOfOtherFinanceExpenses><fsa:TaxExpense contextRef="Per01102012_30092013" decimals="0" unitRef="DKK">162858</fsa:TaxExpense><fsa:ProfitLoss contextRef="Per01102012_30092013" decimals="0" unitRef="DKK">483652</fsa:ProfitLoss><fsa:DisclosureOfEmployeeBenefitsExpense contextRef="Per01102012_30092013">1 Personaleomkostninger &lt;br xmlns="http://www.w3.org/1999/xhtml"/&gt; Lønninger  2.397.988 3.102&lt;br xmlns="http://www.w3.org/1999/xhtml"/&gt; Pensioner  332.301 392&lt;br xmlns="http://www.w3.org/1999/xhtml"/&gt; Andre omkostninger til social sikring  169.175 141&lt;br xmlns="http://www.w3.org/1999/xhtml"/&gt;    &lt;br xmlns="http://www.w3.org/1999/xhtml"/&gt; 2.899.464 3.635&lt;br xmlns="http://www.w3.org/1999/xhtml"/&gt;    &lt;br xmlns="http://www.w3.org/1999/xhtml"/&gt;  &lt;br xmlns="http://www.w3.org/1999/xhtml"/&gt;    &lt;br xmlns="http://www.w3.org/1999/xhtml"/&gt;</fsa:DisclosureOfEmployeeBenefitsExpense><fsa:DisclosureOfDepreciationAmortisationExpenseAndImpairmentLossesOfPropertyPlantAndEquipmentAndIntangibleAssetsRecognisedInProfitOrLoss contextRef="Per01102012_30092013">2 Afskrivning af materielle anlægsaktiver &lt;br xmlns="http://www.w3.org/1999/xhtml"/&gt; Småanskaffelser  45.132 30&lt;br xmlns="http://www.w3.org/1999/xhtml"/&gt; Driftsmateriel  78.897 82&lt;br xmlns="http://www.w3.org/1999/xhtml"/&gt;    &lt;br xmlns="http://www.w3.org/1999/xhtml"/&gt; 124.029 112&lt;br xmlns="http://www.w3.org/1999/xhtml"/&gt;    &lt;br xmlns="http://www.w3.org/1999/xhtml"/&gt;    &lt;br xmlns="http://www.w3.org/1999/xhtml"/&gt;</fsa:DisclosureOfDepreciationAmortisationExpenseAndImpairmentLossesOfPropertyPlantAndEquipmentAndIntangibleAssetsRecognisedInProfitOrLoss><fsa:DisclosureOfTaxExpenses contextRef="Per01102012_30092013">3 Skat af årets resultat &lt;br xmlns="http://www.w3.org/1999/xhtml"/&gt; Beregnet skat af årets resultat  154.125 89&lt;br xmlns="http://www.w3.org/1999/xhtml"/&gt; Regulering af udskudt skat  8.733 -5&lt;br xmlns="http://www.w3.org/1999/xhtml"/&gt;    &lt;br xmlns="http://www.w3.org/1999/xhtml"/&gt; 162.858 84&lt;br xmlns="http://www.w3.org/1999/xhtml"/&gt;    &lt;br xmlns="http://www.w3.org/1999/xhtml"/&gt;    &lt;br xmlns="http://www.w3.org/1999/xhtml"/&gt;</fsa:DisclosureOfTaxExpenses><fsa:DisclosureOfEquity contextRef="Per01102012_30092013">5 Egenkapital &lt;br xmlns="http://www.w3.org/1999/xhtml"/&gt;  &lt;br xmlns="http://www.w3.org/1999/xhtml"/&gt;  &lt;br xmlns="http://www.w3.org/1999/xhtml"/&gt; Virksomhedskapital  80.000 0 0 80.000&lt;br xmlns="http://www.w3.org/1999/xhtml"/&gt; Overført resultat  806.499 0 434.452 1.240.951&lt;br xmlns="http://www.w3.org/1999/xhtml"/&gt; Forslag til udbytte for&lt;br xmlns="http://www.w3.org/1999/xhtml"/&gt; regnskabsåret  48.300 -48.300 49.200 49.200&lt;br xmlns="http://www.w3.org/1999/xhtml"/&gt;        &lt;br xmlns="http://www.w3.org/1999/xhtml"/&gt; 934.799 -48.300 483.652 1.370.151&lt;br xmlns="http://www.w3.org/1999/xhtml"/&gt;        &lt;br xmlns="http://www.w3.org/1999/xhtml"/&gt;  &lt;br xmlns="http://www.w3.org/1999/xhtml"/&gt;   &lt;br xmlns="http://www.w3.org/1999/xhtml"/&gt;   &lt;br xmlns="http://www.w3.org/1999/xhtml"/&gt;     &lt;br xmlns="http://www.w3.org/1999/xhtml"/&gt;</fsa:DisclosureOfEquity><fsa:DisclosureOfShorttermLiabilities contextRef="Per01102012_30092013">6 Selskabsskat &lt;br xmlns="http://www.w3.org/1999/xhtml"/&gt; Selskabsskat, primo  88.575 213&lt;br xmlns="http://www.w3.org/1999/xhtml"/&gt; Skat af årets resultat  154.125 89&lt;br xmlns="http://www.w3.org/1999/xhtml"/&gt; Betalt ordinær acontoskat  -53.000 0&lt;br xmlns="http://www.w3.org/1999/xhtml"/&gt;    &lt;br xmlns="http://www.w3.org/1999/xhtml"/&gt; 189.700 302&lt;br xmlns="http://www.w3.org/1999/xhtml"/&gt;    &lt;br xmlns="http://www.w3.org/1999/xhtml"/&gt;    &lt;br xmlns="http://www.w3.org/1999/xhtml"/&gt;</fsa:DisclosureOfShorttermLiabilities><fsa:InformationOnWithdrawnClaimsOfCreditorForBenefitOfOtherCreditors contextRef="Per01102012_30092013">7 Sikkerhedsstillelser &lt;br xmlns="http://www.w3.org/1999/xhtml"/&gt; Arbejdsgaranti t.kr. 20 er garanteret af Sydbank. Sikringskonti er stillet som sikkerhed herfor.                     &lt;br xmlns="http://www.w3.org/1999/xhtml"/&gt;</fsa:InformationOnWithdrawnClaimsOfCreditorForBenefitOfOtherCreditors><fsa:GrossProfitLoss contextRef="Per01102011_30092012" decimals="-3" unitRef="DKK">4125000</fsa:GrossProfitLoss><fsa:EmployeeBenefitsExpense contextRef="Per01102011_30092012" decimals="-3" unitRef="DKK">3635000</fsa:EmployeeBenefitsExpense><fsa:DepreciationAmortisationExpenseAndImpairmentLossesOfPropertyPlantAndEquipmentAndIntangibleAssetsRecognisedInProfitOrLoss contextRef="Per01102011_30092012" decimals="-3" unitRef="DKK">112000</fsa:DepreciationAmortisationExpenseAndImpairmentLossesOfPropertyPlantAndEquipmentAndIntangibleAssetsRecognisedInProfitOrLoss><fsa:OtherOperatingExpenses contextRef="Per01102011_30092012" decimals="-3" unitRef="DKK">56000</fsa:OtherOperatingExpenses><fsa:ProfitLossFromOrdinaryOperatingActivities contextRef="Per01102011_30092012" decimals="-3" unitRef="DKK">322000</fsa:ProfitLossFromOrdinaryOperatingActivities><fsa:OtherFinanceIncome contextRef="Per01102011_30092012" decimals="-3" unitRef="DKK">14000</fsa:OtherFinanceIncome><fsa:RestOfOtherFinanceExpenses contextRef="Per01102011_30092012" decimals="-3" unitRef="DKK">5000</fsa:RestOfOtherFinanceExpenses><fsa:TaxExpense contextRef="Per01102011_30092012" decimals="-3" unitRef="DKK">84000</fsa:TaxExpense><fsa:ProfitLoss contextRef="Per01102011_30092012" decimals="-3" unitRef="DKK">247000</fsa:ProfitLoss><fsa:FixturesFittingsToolsAndEquipment contextRef="Per01102012_30092013-Instant" decimals="0" unitRef="DKK">225800</fsa:FixturesFittingsToolsAndEquipment><fsa:PropertyPlantAndEquipment contextRef="Per01102012_30092013-Instant" decimals="0" unitRef="DKK">225800</fsa:PropertyPlantAndEquipment><fsa:OtherLongtermReceivables contextRef="Per01102012_30092013-Instant" decimals="0" unitRef="DKK">16836</fsa:OtherLongtermReceivables><fsa:LongtermInvestmentsAndReceivables contextRef="Per01102012_30092013-Instant" decimals="0" unitRef="DKK">16836</fsa:LongtermInvestmentsAndReceivables><fsa:NoncurrentAssets contextRef="Per01102012_30092013-Instant" decimals="0" unitRef="DKK">242636</fsa:NoncurrentAssets><fsa:ManufacturedGoodsAndGoodsForResale contextRef="Per01102012_30092013-Instant" decimals="0" unitRef="DKK">50084</fsa:ManufacturedGoodsAndGoodsForResale><fsa:Inventories contextRef="Per01102012_30092013-Instant" decimals="0" unitRef="DKK">50084</fsa:Inventories><fsa:ShorttermTradeReceivables contextRef="Per01102012_30092013-Instant" decimals="0" unitRef="DKK">659737</fsa:ShorttermTradeReceivables><fsa:ContractWorkInProgress contextRef="Per01102012_30092013-Instant" decimals="0" unitRef="DKK">164672</fsa:ContractWorkInProgress><fsa:ShorttermReceivables contextRef="Per01102012_30092013-Instant" decimals="0" unitRef="DKK">824409</fsa:ShorttermReceivables><fsa:CashAndCashEquivalents contextRef="Per01102012_30092013-Instant" decimals="0" unitRef="DKK">1481712</fsa:CashAndCashEquivalents><fsa:CurrentAssets contextRef="Per01102012_30092013-Instant" decimals="0" unitRef="DKK">2356205</fsa:CurrentAssets><fsa:Assets contextRef="Per01102012_30092013-Instant" decimals="0" unitRef="DKK">2598841</fsa:Assets><fsa:ContributedCapital contextRef="Per01102012_30092013-Instant" decimals="0" unitRef="DKK">80000</fsa:ContributedCapital><fsa:RetainedEarnings contextRef="Per01102012_30092013-Instant" decimals="0" unitRef="DKK">1240951</fsa:RetainedEarnings><fsa:ProposedDividendRecognisedInEquity contextRef="Per01102012_30092013-Instant" decimals="0" unitRef="DKK">49200</fsa:ProposedDividendRecognisedInEquity><fsa:Equity contextRef="Per01102012_30092013-Instant" decimals="0" unitRef="DKK">1370151</fsa:Equity><fsa:ProvisionsForDeferredTax contextRef="Per01102012_30092013-Instant" decimals="0" unitRef="DKK">12129</fsa:ProvisionsForDeferredTax><fsa:Provisions contextRef="Per01102012_30092013-Instant" decimals="0" unitRef="DKK">12129</fsa:Provisions><fsa:ShorttermTradePayables contextRef="Per01102012_30092013-Instant" decimals="0" unitRef="DKK">103380</fsa:ShorttermTradePayables><fsa:ShorttermTaxPayables contextRef="Per01102012_30092013-Instant" decimals="0" unitRef="DKK">189700</fsa:ShorttermTaxPayables><fsa:OtherShorttermPayables contextRef="Per01102012_30092013-Instant" decimals="0" unitRef="DKK">889862</fsa:OtherShorttermPayables><fsa:ShorttermPayablesToShareholdersAndManagement contextRef="Per01102012_30092013-Instant" decimals="0" unitRef="DKK">33619</fsa:ShorttermPayablesToShareholdersAndManagement><fsa:ShorttermLiabilitiesOtherThanProvisions contextRef="Per01102012_30092013-Instant" decimals="0" unitRef="DKK">1216561</fsa:ShorttermLiabilitiesOtherThanProvisions><fsa:LiabilitiesOtherThanProvisions contextRef="Per01102012_30092013-Instant" decimals="0" unitRef="DKK">1216561</fsa:LiabilitiesOtherThanProvisions><fsa:LiabilitiesAndEquity contextRef="Per01102012_30092013-Instant" decimals="0" unitRef="DKK">2598841</fsa:LiabilitiesAndEquity><fsa:FixturesFittingsToolsAndEquipment contextRef="Per01102011_30092012-Instant" decimals="-3" unitRef="DKK">320000</fsa:FixturesFittingsToolsAndEquipment><fsa:PropertyPlantAndEquipment contextRef="Per01102011_30092012-Instant" decimals="-3" unitRef="DKK">320000</fsa:PropertyPlantAndEquipment><fsa:OtherLongtermReceivables contextRef="Per01102011_30092012-Instant" decimals="-3" unitRef="DKK">17000</fsa:OtherLongtermReceivables><fsa:LongtermInvestmentsAndReceivables contextRef="Per01102011_30092012-Instant" decimals="-3" unitRef="DKK">17000</fsa:LongtermInvestmentsAndReceivables><fsa:NoncurrentAssets contextRef="Per01102011_30092012-Instant" decimals="-3" unitRef="DKK">337000</fsa:NoncurrentAssets><fsa:ManufacturedGoodsAndGoodsForResale contextRef="Per01102011_30092012-Instant" decimals="-3" unitRef="DKK">52000</fsa:ManufacturedGoodsAndGoodsForResale><fsa:Inventories contextRef="Per01102011_30092012-Instant" decimals="-3" unitRef="DKK">52000</fsa:Inventories><fsa:ShorttermTradeReceivables contextRef="Per01102011_30092012-Instant" decimals="-3" unitRef="DKK">685000</fsa:ShorttermTradeReceivables><fsa:ContractWorkInProgress contextRef="Per01102011_30092012-Instant" decimals="-3" unitRef="DKK">213000</fsa:ContractWorkInProgress><fsa:ShorttermReceivables contextRef="Per01102011_30092012-Instant" decimals="-3" unitRef="DKK">898000</fsa:ShorttermReceivables><fsa:CashAndCashEquivalents contextRef="Per01102011_30092012-Instant" decimals="-3" unitRef="DKK">1124000</fsa:CashAndCashEquivalents><fsa:CurrentAssets contextRef="Per01102011_30092012-Instant" decimals="-3" unitRef="DKK">2074000</fsa:CurrentAssets><fsa:Assets contextRef="Per01102011_30092012-Instant" decimals="-3" unitRef="DKK">2411000</fsa:Assets><fsa:ContributedCapital contextRef="Per01102011_30092012-Instant" decimals="-3" unitRef="DKK">80000</fsa:ContributedCapital><fsa:RetainedEarnings contextRef="Per01102011_30092012-Instant" decimals="-3" unitRef="DKK">807000</fsa:RetainedEarnings><fsa:ProposedDividendRecognisedInEquity contextRef="Per01102011_30092012-Instant" decimals="-3" unitRef="DKK">48000</fsa:ProposedDividendRecognisedInEquity><fsa:Equity contextRef="Per01102011_30092012-Instant" decimals="-3" unitRef="DKK">935000</fsa:Equity><fsa:ProvisionsForDeferredTax contextRef="Per01102011_30092012-Instant" decimals="-3" unitRef="DKK">4000</fsa:ProvisionsForDeferredTax><fsa:Provisions contextRef="Per01102011_30092012-Instant" decimals="-3" unitRef="DKK">4000</fsa:Provisions><fsa:ShorttermTradePayables contextRef="Per01102011_30092012-Instant" decimals="-3" unitRef="DKK">171000</fsa:ShorttermTradePayables><fsa:ShorttermTaxPayables contextRef="Per01102011_30092012-Instant" decimals="-3" unitRef="DKK">302000</fsa:ShorttermTaxPayables><fsa:OtherShorttermPayables contextRef="Per01102011_30092012-Instant" decimals="-3" unitRef="DKK">966000</fsa:OtherShorttermPayables><fsa:ShorttermPayablesToShareholdersAndManagement contextRef="Per01102011_30092012-Instant" decimals="-3" unitRef="DKK">33000</fsa:ShorttermPayablesToShareholdersAndManagement><fsa:ShorttermLiabilitiesOtherThanProvisions contextRef="Per01102011_30092012-Instant" decimals="-3" unitRef="DKK">1472000</fsa:ShorttermLiabilitiesOtherThanProvisions><fsa:LiabilitiesOtherThanProvisions contextRef="Per01102011_30092012-Instant" decimals="-3" unitRef="DKK">1472000</fsa:LiabilitiesOtherThanProvisions><fsa:LiabilitiesAndEquity contextRef="Per01102011_30092012-Instant" decimals="-3" unitRef="DKK">2411000</fsa:LiabilitiesAndEquity><cmn:NameAndSurnameOfMemberOfExecutiveBoard contextRef="Per01102012_30092013_0_Identifikation_af_medlem_af_direktionen">Casper Holm Nielsen</cmn:NameAndSurnameOfMemberOfExecutiveBoard><cmn:NameAndSurnameOfAuditor contextRef="Per01102012_30092013_1_Identifikation_af_revisor">Tonny Kofoed</cmn:NameAndSurnameOfAuditor><cmn:NameOfAuditFirm contextRef="Per01102012_30092013_1_Identifikation_af_revisor">Rønne Revision, </cmn:NameOfAuditFirm><cmn:DescriptionOfAuditor contextRef="Per01102012_30092013_1_Identifikation_af_revisor">registreret revisor</cmn:DescriptionOfAuditor><fsa:ProfitLoss contextRef="Per01102012_30092013_2_Foreslået_udbytte_indregnet_under_gældsforpligtelser" decimals="0" unitRef="DKK">49200</fsa:ProfitLoss><fsa:ProfitLoss contextRef="Per01102012_30092013_3_Overført_resultat" decimals="0" unitRef="DKK">434452</fsa:ProfitLoss><fsa:ProfitLoss contextRef="Per01102011_30092012_0_Foreslået_udbytte_indregnet_under_gældsforpligtelser" decimals="-3" unitRef="DKK">48000</fsa:ProfitLoss><fsa:ProfitLoss contextRef="Per01102011_30092012_1_Overført_resultat" decimals="-3" unitRef="DKK">199000</fsa:ProfitLoss></xbrl>